Workbook

Sheet Read Me
A1: Lio (formerly askLio) — Event Participation & ICP Analysis
A3: Compiled | B3: 2026-07-20 · corrected 2026-08-31
A4: Method | B4: Web research across lio.ai (events page, event landing pages, newsroom), Livestorm, organizer sites (DPW, BME, WBR/ProcureCon, SSON, Procurement Leaders, Handelsblatt, KonnectHouse, Procurement Summit), press, LinkedIn recaps, YC/BMWK/VivaTech records. Every row carries its source URL.
A5: Tabs | B5: Events Master (all 49 events/appearances) · Event Categorization (counts & funnel logic — formulas live off Events Master) · Company Firmographics (verified table + directional block) · ICP Analysis (pattern synthesis)
A7: Confidence legend (Events Master, col Q)
A8: Confirmed | B8: Independently verified on organizer/press side or on a Lio property with specifics
A9: Intent | B9: Listed on lio.ai/events calendar only — organizer-side confirmation not retrievable
A10: Unconfirmed | B10: Plausible but no solid source
A12: Key caveats
A13: 1 | B13: Company-reported figures (attendee counts at own events, adoption metrics) are marked as such in Key details.
A14: 2 | B14: Bots & Buyers 2025 date (Oct 30, 2025) per external-agent finding; Keil's post timestamp implies late Oct/early Nov — treated as Oct 30, 2025.
A15: 3 | B15: askLio won the DPW 'Growth Stage' Award 2025 (category for $2–10M ARR vendors) — some recaps call it 'DPW Innovation Award'; same award program.
A16: 4 | B16: Firmographics second block (Clubhouse attendees) is industry-classification only — revenue/employees not verified in this pass.
A17: 5 | B17: Walmart = engagement/endorser, not a confirmed customer.
A18: 6 | B18: Bots & Buyers correction (2026-08-31): the EU flagship was recorded as Sep 23–24 in Munich (presumed, venue TBA). Organizer verification moved it to Oct 27–28 at MotorWorld München — colliding with SIG Chicago (Oct 25–28), not ProcureCon Europe Cologne — and added a separate US edition, Bots & Buyers NYC on Sep 23. See 16-event-status-update.md.

Sheet Events Master
A1: # | B1: Event | C1: Franchise / Series | D1: Category | E1: Organizer | F1: Year | G1: Date(s) | H1: City | I1: Venue | J1: Country | K1: Region | L1: Format | M1: Delivery | N1: Language | O1: Lio role | P1: Status | Q1: Confidence | R1: What it's about | S1: Who attends (audience profile) | T1: Scale (attendees) | U1: Named companies present | V1: Lio people involved | W1: Key details / intel | X1: Source URL
A2: 1 | B2: Bots & Buyers Munich 2025 (1st edition) | C2: Bots & Buyers | D2: Own community flagship | E2: Lio (askLio) | F2: 2025 | G2: Oct 30, 2025 | H2: Munich | I2: askLio office | J2: DE | K2: DACH | L2: Community event | M2: In-person | N2: EN | O2: Host | P2: Past | Q2: Confirmed | R2: Launch venue for the 'Multi Agent System for Procurement'; 'Agent Experience World' with 14 live agent demos | S2: Invited procurement leaders (DACH/EU) | T2: ~150–170 (company-reported; 150 per Keil, '170+' per team recap) | U2: Not individually published | V2: Vladimir Keil + engineering team | W2: Category-first product launch; feedback 'only bad thing: just one day' drove 2-day 2026 Summit format; metrics pitched: 10% savings, 95% adoption, 85% ops automated | X2: https://www.linkedin.com/posts/vladimir-keil_category-first-asklio-lauched-the-multi-activity-7392551482727837696-00hJ
A3: 2 | B3: Bots & Buyers Munich 2026: Clubhouse Edition | C3: Bots & Buyers | D3: Own community flagship | E3: Lio | F3: 2026 | G3: Jun 11, 2026 | H3: Munich | I3: Lio HQ 'Clubhouse', Seidlstr. 23 | J3: DE | K3: DACH | L3: Community event | M3: In-person | N3: EN | O3: Host | P3: Past | Q3: Confirmed | R3: Full-day community event; 'Agentic Experience World' — agents across procurement, logistics, finance | S3: Invited European procurement leaders | T3: ~200 professionals + ~100 Lio staff (company-reported) | U3: BASF, Benteler, Breuninger, Deutsche Bahn, Dormakaba, FlixBus, IMS Gear, Lufthansa, Munich Re, Nemetschek, NEW AG, Pfalzwerke, Rehau, Schaeffler, Scheidt & Bachmann, Schott, Seidel, Speira, SWM, SWMH, Toi Toi & Dixi, TÜV, Webasto | V3: Vladimir Keil; organized in-house by Jill Therese Stäbe | W3: CPO attendee quote: 'This feels at least 5 years ahead of everything I've seen so far'; closing announcement of The Summit (Sep 23–24, 2026) | X3: https://lio.ai/bots-buyers-clubhouse-edition
A4: 3 | B4: Bots & Buyers 2026 EU — The Summit | C4: Bots & Buyers | D4: Own community flagship | E4: Lio | F4: 2026 | G4: Oct 27–28, 2026 | H4: Munich | I4: MotorWorld München (Munich-Freimann) | J4: DE | K4: DACH | L4: Community summit | M4: In-person | N4: EN | O4: Host | P4: Upcoming | Q4: Confirmed (organizer-verified 2026-08-31) | R4: First 2-day edition of the flagship community franchise; billed as "the most AI-focused procurement event on earth" | S4: Procurement elite (invite/waitlist) | T4: TBA | U4: TBA | V4: TBA | W4: CORRECTED 2026-08-31: previously recorded as Sep 23–24 in Munich (presumed, venue TBA) — organizer verification moved it to Oct 27–28 at MotorWorld München. It therefore COLLIDES with SIG Chicago (Oct 25–28), not with ProcureCon Europe Cologne. Direct response to the #1 attendee complaint about the 1-day format. Excluded from the P1 budget as an own event, but not from the calendar conflict. | X4: https://bots-and-buyers-eu.lio.ai/
A5: 4 | B5: Bots & Buyers US 2026 | C5: Bots & Buyers | D5: Own community flagship | E5: Lio | F5: 2026 | G5: TBA (teased since Nov 2025) | H5: US TBA | I5: TBA | J5: US | K5: US | L5: Community event | M5: In-person | N5: EN | O5: Host | P5: Announced (TBA) | Q5: Confirmed (announced) | R5: US edition: connect industry experts, encourage partnerships, discuss procurement roadmap | S5: US procurement leaders | T5: TBA | U5: TBA | V5: TBA | W5: Signals US community-GTM replication of the Munich playbook | X5: https://lio.ai/events (signup: lio-ai.typeform.com/to/CIS8V08o)
A6: 5 | B6: Procurement Agentic AI Leaders Dinner (Miami) | C6: CPO Dinners (US) | D6: Own executive dinner | E6: Lio | F6: 2026 | G6: Apr 14, 2026 | H6: Miami | I6: Undisclosed (Apple Maps link) | J6: US | K6: US | L6: Private dinner | M6: In-person | N6: EN | O6: Host | P6: Past | Q6: Confirmed | R6: Agentic AI for senior procurement execs; sidecar to NAPES (Apr 13) | S6: Select senior procurement leaders, invitation-only | T6: Small private group | U6: Walmart (co-host affiliation) | V6: Jared Petras, Vladimir Keil, Till Wagner | W6: Held on day 2 of Petras's Lio tenure (appointed Head of US Growth eff. Apr 13); page still titled him Walmart Sr. Director | X6: https://lio.ai/lio-exclusive-cpo-dinner-2026
A7: 6 | B7: Procurement Agentic AI Leaders Dinner — DPW Edition (NYC) | C7: CPO Dinners (US) | D7: Own executive dinner | E7: Lio | F7: 2026 | G7: Jun 2, 2026 | H7: New York | I7: Undisclosed | J7: US | K7: US | L7: Private dinner | M7: In-person | N7: EN | O7: Host | P7: Past | Q7: Confirmed | R7: Night-before-DPW-New-York dinner; framed on 2-year Walmart partnership + a16z backing | S7: Senior procurement leaders, invitation-only (Typeform RSVP) | T7: Small private group | U7: Walmart, a16z (referenced on page) | V7: Jared Petras, Vladimir Keil, Till Wagner | W7: NOT on DPW's official side-events list (hosts there: Zip, ORO Labs, Deloitte etc.) — deliberately private | X7: https://lio.ai/lio-exclusive-cpo-dinner-dpw-edition
A8: 7 | B8: The Lio Principals — BME eLösungstage 2026 Edition | C8: The Lio Principals (EU) | D8: Own executive dinner | E8: Lio | F8: 2026 | G8: May 19, 2026, 7:30 PM | H8: Düsseldorf | I8: Undisclosed | J8: DE | K8: DACH | L8: Private dinner | M8: In-person | N8: DE/EN | O8: Host | P8: Past | Q8: Confirmed | R8: Deepen the conversations of the eLösungstage day; peer connection | S8: 'Carefully selected' senior procurement peers, invitation-only | T8: Small private group | U8: Not published | V8: Not published | W8: European mirror of the US dinner circuit; same-week cadence as WPC dinner | X8: https://lio.ai/the-lio-principals-bme-e-loesungstage-2026-edition
A9: 8 | B9: The Lio Principals — World Procurement Congress 2026 Edition | C9: The Lio Principals (EU) | D9: Own executive dinner | E9: Lio | F9: 2026 | G9: May 20, 2026, 8:15 PM | H9: London | I9: Gaucho at The O2, Peninsula Square | J9: UK | K9: UK | L9: Private dinner | M9: In-person | N9: EN | O9: Host | P9: Past | Q9: Confirmed | R9: Sidecar dinner during World Procurement Congress | S9: Select senior procurement leaders, invitation-only (Typeform confirm) | T9: Small private group | U9: Not published | V9: Not published | W9: Targets WPC's 70%-director+ audience | X9: https://lio.ai/the-lio-principals-world-procurement-congress-2026-edition
A10: 9 | B10: FDE Night 2026 | C10: Technical community | D10: Own technical/GTM community | E10: Lio | F10: 2026 | G10: TBA | H10: Europe TBA | I10: TBA | J10: TBA | K10: EU | L10: Community meetup | M10: In-person | N10: EN | O10: Host | P10: Announced (TBA) | Q10: Confirmed (announced) | R10: Meetup for Forward Deployed Engineers, technical operators, and those exploring the FDE role in Europe | S10: FDEs, technical operators, AI engineers | T10: TBA | U10: TBA | V10: TBA | W10: Talent/brand play matching Lio's Palantir-style FDE hiring push | X10: https://lio.ai/events (signup: lio-ai.typeform.com/to/ASJN0iqE)
A11: 10 | B11: Fireside Chat w/ a16z: 'Winning Global Enterprises — The GTM Playbook for AI Agents' | C11: GTM community | D11: Own technical/GTM community | E11: Lio + a16z | F11: 2026 | G11: TBA | H11: TBA | I11: TBA | J11: TBA | K11: EU | L11: Fireside chat | M11: In-person | N11: EN | O11: Host | P11: Announced (TBA) | Q11: Confirmed (announced) | R11: GTM for AI agents with representatives of a16z + Lio founding team | S11: Founders, operators, GTM leaders | T11: TBA | U11: a16z | V11: Founding team (Keil, Wagner, Heinzmann) + a16z reps | W11: Page copy: 'a16z is finally investing into a European startup again - us!' | X11: https://lio.ai/events (signup: lio-ai.typeform.com/to/bewwETDX)
A12: 11 | B12: Hackathon: Agentic AI | C12: Technical community | D12: Own technical/GTM community | E12: Lio | F12: 2026 | G12: TBA | H12: TBA | I12: TBA | J12: TBA | K12: EU | L12: Hackathon | M12: In-person | N12: EN | O12: Host | P12: Announced (TBA) | Q12: Confirmed (announced) | R12: 'Solve the hardest technical problems with AI' | S12: Engineers, students, AI builders | T12: TBA | U12: TBA | V12: TBA | W12: Engineering-brand + recruiting funnel | X12: https://lio.ai/events (signup: lio-ai.typeform.com/to/grXj3ZTD)
A13: 12 | B13: Die Zukunft von AI-Agents im Einkauf | C13: Webinar series (DE/EN pairs) | D13: Own webinar | E13: Lio | F13: 2026 | G13: Apr 30, 2026, 3:00 PM CEST | H13: Online | I13: Livestorm | J13: — | K13: Online | L13: Webinar | M13: Online | N13: DE | O13: Host | P13: Past | Q13: Confirmed | R13: What the next 24 months of AI agents in procurement look like | S13: German-speaking CPOs & procurement leaders | T13: Not published | U13: — | V13: Speakers not published (Patrick Hasse associated via LinkedIn promo — unconfirmed) | W13: Weekly DE/EN pairing, Apr–May 2026; themes mirror newsroom content pillars | X13: https://app.livestorm.co/lio
... A50: 49 | B50: Bots & Buyers NYC 2026 | C50: Bots & Buyers | D50: Own community flagship | E50: Lio | F50: 2026 | G50: Sep 23, 2026 | H50: New York | I50: TBA | J50: US | K50: US | L50: Community summit | M50: In-person | N50: EN | O50: Host | P50: Upcoming | Q50: Confirmed (organizer-verified 2026-08-31) | R50: First US edition of the flagship community franchise — free and application-only: live agents, trainings, CPO panels, the Lio Awards | S50: 500+ curated procurement leaders (application-only) | T50: 500+ (curated) | U50: TBA | V50: TBA (US pod — Petras) | W50: Lands MID-GAUNTLET between ProcureCon Europe Cologne (Sep 22–24) and ProcureCon East Boston (Sep 28–30) — it competes for the US pod, not the DACH squad. Added 2026-08-31 on organizer verification; the franchise went transatlantic after this workbook was compiled. | X50: https://lio.ai/events

Sheet Event Categorization
A1: Event Categorization & Funnel Logic
A2: Counts are live formulas over the Events Master tab.
A4: Category | B4: Events in bucket | C4: Strategic purpose | D4: Who is in the room | E4: Funnel role | F4: Count (live)
A5: Own community flagship | B5: Bots & Buyers (4 editions: 2025, Clubhouse 2026, The Summit 2026, US 2026) | C5: Category creation + product feedback + pipeline warm-up; puts prospects in a room with Lio engineers and live agents | D5: Invited procurement leaders of European (soon US) enterprises | E5: Demand gen / community (top + mid funnel) | F5: =COUNTIF('Events Master'!$D$2:$D$50,A5)
A6: Own executive dinner | B6: CPO Dinners (Miami, NYC) + The Lio Principals (Düsseldorf, London) | C6: ABM: 8–20 C-level guests, conference-sidecar timing, Walmart/a16z halo | D6: CPOs & senior procurement execs of Global 2000 | E6: ABM / late-funnel acceleration | F6: =COUNTIF('Events Master'!$D$2:$D$50,A6)
A7: Own webinar | B7: 8 sessions Apr–May 2026 in strict DE/EN pairs (Future of AI Agents, Radical Simplicity, BPO to Bots, Stop Leaking Savings) | C7: Content engine mirroring the newsroom pillars; captures mid-funnel interest in both core languages | D7: Procurement teams, ops/GBS leaders, requesters | E7: Mid-funnel nurture | F7: =COUNTIF('Events Master'!$D$2:$D$50,A7)
A8: Own technical/GTM community | B8: FDE Night, Agentic AI Hackathon, a16z GTM Fireside (all TBA) | C8: Employer brand + engineering credibility + founder-scene positioning | D8: Engineers, FDEs, founders, operators | E8: Talent + brand | F8: =COUNTIF('Events Master'!$D$2:$D$50,A8)
A9: Sponsorship / exhibition | B9: DPW NY (booth 10), BME eLösungstage 25/26, ProcureCon East (LEAD sponsor), Procurement Summit (C09), WPC, NAPES, Handelsblatt, KonnectHouse FFM, ProcureCon Connect US, DPW Ams 26 | C9: Booth presence where buying committees congregate; escalating tiers (lead sponsor at ProcureCon East) | D9: Conference-specific — see Events Master | E9: Awareness + lead gen | F9: =COUNTIF('Events Master'!$D$2:$D$50,A9)
A10: Speaker / thought leadership | B10: Keil roadshow: ProcureCon West/Connect, SSOW, APC, P&SC LIVE, Procurement Summit 24/25, KonnectHouse NYC, webinars-as-guest | C10: One repeatable keynote ('Humans vs. AI Agents: Who Runs Procurement in 2026?') delivered across every major stage; CEO as category evangelist | D10: CPO-to-practitioner depending on stage | E10: Authority + demand gen | F10: =COUNTIF('Events Master'!$D$2:$D$50,A10)
A11: Award / recognition | B11: DPW Growth Stage Award 2025, BME Excellence Award 2024 (with REHAU), Digital-Gipfel Gründungspreis 2023, VivaTech Top 100 2026 | C11: Third-party validation ladder: government prize → association award with customer → industry award by CPO jury → European ranking | D11: Juries of CPOs, ministries, ecosystem | E11: Credibility / social proof | F11: =COUNTIF('Events Master'!$D$2:$D$50,A11)
A12: Private roundtable / ABM | B12: World 50 Procurement Accelerator | C12: Ultra-curated access to Fortune 500 procurement execs | D12: World 50 member executives | E12: ABM (highest tier) | F12: =COUNTIF('Events Master'!$D$2:$D$50,A12)
A13: Accelerator / program | B13: Y Combinator S23 | C13: Origin credential; still used in every bio and job ad | D13: Investors | E13: Fundraise / brand | F13: =COUNTIF('Events Master'!$D$2:$D$50,A13)
A14: Campus / talent | B14: TUM.ai E-Lab, LSESU German Society | C14: Graduate talent pipeline in Munich + London | D14: Students | E14: Recruiting | F14: =COUNTIF('Events Master'!$D$2:$D$50,A14)
A15: TOTAL | F15: =SUM(F5:F14)
A17: Counts by region
A18: DACH | B18: =COUNTIF('Events Master'!$K$2:$K$50,A18)
A19: US | B19: =COUNTIF('Events Master'!$K$2:$K$50,A19)
A20: EU | B20: =COUNTIF('Events Master'!$K$2:$K$50,A20)
A21: UK | B21: =COUNTIF('Events Master'!$K$2:$K$50,A21)
A22: Online | B22: =COUNTIF('Events Master'!$K$2:$K$50,A22)
A24: Counts by year
A25: 2023 | B25: =COUNTIF('Events Master'!$F$2:$F$50,2023)
A26: 2024 | B26: =COUNTIF('Events Master'!$F$2:$F$50,2024)
A27: 2025 | B27: =COUNTIF('Events Master'!$F$2:$F$50,2025)
A28: 2026 | B28: =COUNTIF('Events Master'!$F$2:$F$50,2026)
A30: Counts by status
A31: Past | B31: =COUNTIF('Events Master'!$P$2:$P$50,A31)
A32: Upcoming | B32: =COUNTIF('Events Master'!$P$2:$P$50,A32)
A33: Announced (TBA) | B33: =COUNTIF('Events Master'!$P$2:$P$50,A33)
A35: Read of the pattern
A36: 2023–2024: credibility building (YC, government prize, first German speaker slots). 2025: DACH trade-fair presence + first own event + DPW award. 2026: full-scale dual-track machine — US blitz (9+ US events in H1 2026 vs zero before Nov 2025) + DACH defense + own franchises scaling to 2-day summit.
A37: Signature play: conference-sidecar private dinners (NAPES→Miami dinner, DPW NY→NYC dinner, BME→Düsseldorf dinner, WPC→London dinner) — buy the audience aggregation, own the intimate conversation.
A38: Every US speaker slot carries the same keynote title ('Humans vs. AI Agents…') and the SSOW titles are undisguised BPO-displacement pitches ('Your BPO Costs 93% Too Much') — event strategy = distribution for exactly two messages: agent workforce + BPO replacement.

Sheet Company Firmographics
A1: Companies in Lio's orbit — firmographics
A2: Block 1 = verified (sources cited). Block 2 = Clubhouse-event attendees, industry classification only — NOT independently verified. Revenue: ins. rev. = insurance revenue (IFRS 17).
A4: Company | B4: Relationship | C4: Industry | D4: HQ | E4: Revenue (latest) | F4: Employees | G4: Ownership | H4: Revenue band | I4: Notes | J4: Source
A5: Munich Re | B5: Customer (flagship) | C5: Reinsurance / insurance | D5: Munich, DE | E5: €60.4B ins. rev. (2025) | F5: ~44,000 | G5: Listed (DAX) | H5: €20B+ | I5: 'World's largest reinsurer'; parent of ERGO; 100% indirect spend | J5: munichre.com media release 2026-02-26
A6: Schaeffler | B6: Customer (COO testimonial) | C6: Automotive & industrial supplier | D6: Herzogenaurach, DE | E6: €23.5B (2025) | F6: 110,753 | G6: Listed; family-controlled | H6: €20B+ | I6: COO Andreas Schick quote; post-Vitesco merger; co-development MOU per LinkedIn | J6: schaeffler.com PR
A7: ERGO Group | B7: Customer | C7: Primary insurance | D7: Düsseldorf, DE | E7: €20.8B ins. rev. (2024) | F7: ~37,000 | G7: Munich Re subsidiary | H7: €20B+ | I7: Customer instance ergo.asklio.ai observed | J7: ergo.com facts & figures
A8: Zeiss | B8: Customer (logo) | C8: Optics / photonics / semicon equipment | D8: Oberkochen, DE | E8: €11.9B (FY2024/25) | F8: ~46,600 | G8: Foundation-owned | H8: €5–20B | J8: zeiss.com PR
A9: Mahle | B9: Customer (logo) | C9: Automotive parts | D9: Stuttgart, DE | E9: €11.7B (2024) | F9: ~67,700 | G9: Foundation-owned | H9: €5–20B | I9: ICE-transition cost pressure | J9: globaldata / Wikipedia
A10: Brose | B10: Customer (named in Series A PR) | C10: Automotive mechatronics | D10: Coburg, DE | E10: €7.7B (2024) | F10: ~30,000–33,000 | G10: Family-owned | H10: €5–20B | I10: Top-5 family-owned auto supplier | J10: brose.com PR
A11: Bilfinger | B11: Customer (logo) | C11: Industrial services | D11: Mannheim, DE | E11: €5.43B (2025) | F11: ~30,600 | G11: Listed | H11: €5–20B | I11: CPO speaks at Handelsblatt CPO Summit | J11: bilfinger.com PR
A12: Diehl | B12: Customer (logo) | C12: Defence / aviation / metering | D12: Nuremberg, DE | E12: €4.7B (2024) | F12: ~18,700 | G12: Family-owned | H12: €1–5B | I12: Defence boom; compliance-heavy procurement | J12: diehl.com PR
A13: Galenica | B13: Customer (logo) | C13: Pharmacy retail & wholesale | D13: Bern, CH | E13: CHF 4.14B (2025) | F13: ~7,900 | G13: Listed (SIX) | H13: €1–5B | I13: Swiss market leader | J13: report.galenica.com
A14: Novonesis (Novozymes) | B14: Customer (named in Series A PR) | C14: Biosolutions | D14: Copenhagen, DK | E14: ~€4.05B (2025) | F14: ~11,820 | G14: Listed; Novo Holdings anchor | H14: €1–5B | I14: Only Nordic logo | J14: novonesis.com PR
A15: TÜV SÜD | B15: Customer (testimonial) | C15: Testing / inspection / certification | D15: Munich, DE | E15: €3.4B (2024) | F15: ~30,000 | G15: Foundation/association-owned | H15: €1–5B | I15: Anna Tillmann quote (Lio Assistant knowledge base); Handelsblatt advertorial case | J15: tuvsud.com PR
A16: ams-OSRAM | B16: Customer (logo) | C16: Optical semiconductors | D16: Premstätten, AT / Munich | E16: €3.3B (2025) | F16: ~19,000 | G16: Listed (SIX) | H16: €1–5B | I16: Restructuring → savings-receptive | J16: ams-osram.com PR
A17: REHAU | B17: Customer (award case) | C17: Polymer processing | D17: Muri bei Bern, CH | E17: ~€3B (est.) | F17: ~20,000 | G17: Family-owned | H17: €1–5B | I17: BME Excellence Award 2024 with askLio; value 4.5x cost, 150+ locations | J17: rehau.com / bme.de
A18: Dormakaba | B18: Customer (logo) | C18: Access solutions | D18: Rümlang, CH | E18: CHF 2.87B (FY2024/25) | F18: ~15,350 | G18: Listed; family anchor | H18: €1–5B | I18: World #3 access solutions; also Clubhouse attendee | J18: report.dormakaba.com
A19: Schott | B19: Customer (logo) | C19: Specialty glass | D19: Mainz, DE | E19: €2.83B (FY2025) | F19: ~17,400 | G19: Foundation-owned | H19: €1–5B | I19: Sister of Zeiss; also Clubhouse attendee | J19: schott.com PR
A20: AL-KO Vehicle Technology | B20: Customer (subdomain observed) | C20: Trailer chassis / RV components | D20: Kötz, DE | E20: ~€740M (est.) | F20: ~3,000 | G20: PE-owned (DexKo / KPS) | H20: <€1B | I20: Customer instance alko.asklio.ai; only PE-owned logo | J20: alko-tech.com / prospeo.io
... A26: Nemetschek | B26: Event attendee | C26: AEC software | D26: Munich, DE | E26: €1.19B (2025) | F26: ~4,100 | G26: Listed; family/foundation anchor | H26: €1–5B | I26: Munich neighbor; Clubhouse attendee | J26: nemetschek.com PR
A28: Block 2 — Clubhouse Edition attendees (Jun 2026), industry classification only — figures NOT verified in this pass
A29: Company | B29: Relationship | C29: Industry (commonly known) | D29: HQ | I29: Notes
A30: Benteler | B30: Event attendee (Clubhouse) | C30: Automotive & steel/tube | D30: Salzburg, AT / Paderborn, DE | E30: n/v | F30: n/v | G30: n/v | H30: n/v | I30: Family-owned; multi-€B auto supplier | J30: lio.ai/bots-buyers-clubhouse-edition
A31: Breuninger | B31: Event attendee (Clubhouse) | C31: Premium department-store retail | D31: Stuttgart, DE | E31: n/v | F31: n/v | G31: n/v | H31: n/v | I31: Acquired by CVC-led consortium (2024) | J31: lio.ai/bots-buyers-clubhouse-edition
A32: FlixBus / Flix | B32: Event attendee (Clubhouse) | C32: Mobility platform (bus/rail) | D32: Munich, DE | E32: n/v | F32: n/v | G32: n/v | H32: n/v | I32: VC/PE-backed scale-up | J32: lio.ai/bots-buyers-clubhouse-edition
A33: IMS Gear | B33: Event attendee (Clubhouse) | C33: Gear/actuator components | D33: Donaueschingen, DE | E33: n/v | F33: n/v | G33: n/v | H33: n/v | I33: Family-owned Mittelstand | J33: lio.ai/bots-buyers-clubhouse-edition
A34: NEW AG | B34: Event attendee (Clubhouse) | C34: Regional utility | D34: Mönchengladbach, DE | E34: n/v | F34: n/v | G34: n/v | H34: n/v | I34: Municipal-anchored | J34: lio.ai/bots-buyers-clubhouse-edition
A35: Pfalzwerke | B35: Event attendee (Clubhouse) | C35: Regional utility / energy | D35: Ludwigshafen, DE | E35: n/v | F35: n/v | G35: n/v | H35: n/v | I35: Municipal/regional shareholders | J35: lio.ai/bots-buyers-clubhouse-edition
A36: Scheidt & Bachmann | B36: Event attendee (Clubhouse) | C36: Fare collection / parking / signalling systems | D36: Mönchengladbach, DE | E36: n/v | F36: n/v | G36: n/v | H36: n/v | I36: Family-owned | J36: lio.ai/bots-buyers-clubhouse-edition
A37: Seidel | B37: Event attendee (Clubhouse) | C37: Metal packaging (cosmetics) — likely Seidel GmbH | D37: Marburg, DE (likely) | E37: n/v | F37: n/v | G37: n/v | H37: n/v | I37: Identity not fully verified | J37: lio.ai/bots-buyers-clubhouse-edition
A38: Speira | B38: Event attendee (Clubhouse) | C38: Aluminium rolling & recycling | D38: Grevenbroich, DE | E38: n/v | F38: n/v | G38: n/v | H38: n/v | I38: PE-owned (KPS) | J38: lio.ai/bots-buyers-clubhouse-edition
A39: SWM (Stadtwerke München) | B39: Event attendee (Clubhouse) | C39: Municipal utility | D39: Munich, DE | E39: n/v | F39: n/v | G39: n/v | H39: n/v | I39: City of Munich-owned | J39: lio.ai/bots-buyers-clubhouse-edition
A40: SWMH (Süddeutscher Verlag) | B40: Event attendee (Clubhouse) | C40: Media holding | D40: Stuttgart/Munich, DE | E40: n/v | F40: n/v | G40: n/v | H40: n/v | I40: Private holding | J40: lio.ai/bots-buyers-clubhouse-edition
A41: Toi Toi & Dixi | B41: Event attendee (Clubhouse) | C41: Mobile sanitation services | D41: Ratingen, DE | E41: n/v | F41: n/v | G41: n/v | H41: n/v | I41: ADCO Group (family) | J41: lio.ai/bots-buyers-clubhouse-edition
A42: Webasto | B42: Event attendee (Clubhouse) | C42: Automotive roofs / thermal / charging | D42: Stockdorf, DE | E42: n/v | F42: n/v | G42: n/v | H42: n/v | I42: Family-owned | J42: lio.ai/bots-buyers-clubhouse-edition

Sheet ICP Analysis
A1: Lio ICP Analysis — pattern synthesis from events + customers + firmographics
A3: 1 · PRIMARY ICP — the DACH industrial backbone
A4: Who | B4: German-speaking enterprise (DE/CH/AT), €2–12B revenue, 15,000–50,000 employees — the modal band of the current logo wall (8 of 17 logos sit in €1–5B, 4 in €5–20B)
A5: Industry | B5: Automotive & discrete manufacturing (Schaeffler, Brose, Mahle, Webasto, Benteler, IMS Gear, AL-KO, ams-OSRAM, Diehl, Dormakaba) + materials/optics/process (Zeiss, Schott, REHAU, Speira) — cost-down culture, EV-transition margin pressure makes '10% incremental savings' land
A6: Ownership | B6: STANDOUT TRAIT: ~two-thirds family-, foundation-, or PE-owned (not free-float). Long-horizon owners, conviction-driven decisions (COO/CFO sponsor), conservative SAP-centric IT estates → 'overlay, don't replace' resonates
A7: Systems | B7: SAP ERP baseline, often Ariba/Coupa present; 100+ person procurement functions; works councils (why 'give time back' framing + BPO-first displacement matters)
A8: Buying center | B8: CPO (sponsor) + COO/CFO (economic buyer, BPO line) + Head of Procurement Excellence/Digitalization (champion) + CIO/CISO (gatekeeper: ISO 27001/GDPR/Azure-EU story)
A9: 2 · SECONDARY ICP — indirect-heavy financial services
A10: Who | B10: Insurers/FS €20B+ (Munich Re, ERGO): 100% indirect spend, high willingness to pay for automation, low direct-materials complexity — fastest 'Agentic BPO' math
A11: Signal | B11: 2 of the 3 flagship named customers are insurance; services firms (TÜV SÜD, Bilfinger) rhyme with this profile
A12: 3 · EMERGING ICP — US Fortune 500 indirect (2026 push)
A13: Who | B13: US enterprises with large GBS/BPO procurement operations — the SSOW Orlando audience; Walmart engagement + Petras hire as beachhead credibility
A14: Evidence | B14: 9+ US events in H1 2026 (vs zero pre-Nov 2025); NYC sales pod; ProcureCon East LEAD sponsorship (Sep 2026); DPW NY triple presence + private CPO dinner
A15: 4 · Utilities & mobility — quiet fourth cluster
A16: Who | B16: Clubhouse attendee mix reveals: SWM, NEW AG, Pfalzwerke (utilities), Deutsche Bahn, Lufthansa, FlixBus (mobility) — regulated, process-heavy, German, public-procurement-adjacent. Directional (event interest ≠ customers yet; DB is a named pilot)
A17: 5 · Where to find them (watering holes, ranked by Lio's own investment)
A18: Watering hole | B18: Why it matters / audience
A19: BME network (eLösungstage, Symposium, Excellence Award) | B19: 13,000-member German association; ~1,000 at eLösungstage; the DACH operating layer (heads-of + managers). Lio: exhibitor 2025 → official partner 2026 + award 2024 + sidecar dinner
A20: DPW (Amsterdam + New York) | B20: 1,700–2,500 digital-procurement decision-makers, CPO/VP-heavy, €2.2K ticket; the transformation elite + VC/vendor ecosystem. Lio: 2025 award winner, 2026 NY sponsor+booth+speaker
A21: Handelsblatt CPO Summit | B21: ~150–250 German C-levels, €2.5K, Chatham House; highest CPO density in DE. Lio: calendar-listed sponsor + 2 placed articles
A22: ProcureCon circuit (West, Connect EU/US, East) | B22: US indirect-procurement establishment, majority director+; Lio escalated to LEAD sponsor at East 2026 alongside SAP/Coupa/GEP
A23: SSOW / SSON | B23: GBS/SSC/BPO buyers — the audience that owns the BPO line item Lio attacks ('Your BPO Costs 93% Too Much')
A24: Procurement Leaders (WPC London, APC New Orleans, World 50) | B24: Most senior peer network; 70% director+; membership-gated ABM
A25: Procurement Summit Hamburg | B25: ~2,300 German practitioners; 3 consecutive years of Keil on stage — mid-market + enterprise DACH reach
A26: Own franchises (Bots & Buyers, dinners, webinars) | B26: The conversion layer: aggregate the above audiences into owned rooms (150→300 people; 2-day Summit Sep 2026)
A28: 6 · Strategic reads (consultant notes)
A29: ARR triangulation | B29: DPW Growth Stage Award (Oct 2025) = $2–10M ARR band + VivaTech Top-100 criterion (Mar 2026) = ≥€5M ARR in 2025 + 'now above Growth-Stage band' for 2026 awards → best estimate ~€5–10M ARR end-2025, growing. No official figure exists.
A30: Event strategy signature | B30: Conference-sidecar dinners: rent the audience aggregation (NAPES, DPW NY, BME, WPC), own the intimate room. Cheap, repeatable, C-level.
A31: Message discipline | B31: One keynote title toured worldwide ('Humans vs. AI Agents: Who Runs Procurement in 2026?'); SSOW titles are naked BPO-displacement pitches. Two messages only: agent workforce + BPO replacement.
A32: DE/EN pairing | B32: Every webinar shipped as a German + English twin — dual-market GTM run as a system, not translation afterthought.
A33: ICP in one sentence | B33: A German-speaking (or US-GBS-heavy) enterprise of €2–20B revenue with an SAP estate, a 100+ person procurement function or BPO contract, long-horizon family/foundation ownership, whose CPO attends BME/DPW/Handelsblatt — reachable via exactly the circuit Lio sponsors, then converted in a Bots & Buyers room or a Principals dinner.
