Workbook

Sheet Read Me
A1: Lio ICP Prospect List
A3: What this is | B3: Named-buyer prospect list for Lio (lio.ai), sourced against the ICP reverse-engineered in the Lio knowledge base (file 10-events-and-icp.md). Built 2026-08-31 as part of Abir Khan's founders-associate application package.
A4: How it was sourced | B4: Apollo.io People & Organization Search with explicit firmographic/title filters per segment (filters documented in 13-icp-prospect-list.md), then per-person enrichment via Apollo People Match to reveal full names, work emails and LinkedIn URLs.
A5: Coverage vs totals | B5: The list holds 219 named contacts at 122 companies. Apollo reports 2,245 titled buyers / 1,933 companies matching the same filters in total - the list is the top slice (pages 1-2 per search), and the search filters are reusable to refill it.
A6: Cost transparency | B6: Enrichment consumed 219 Apollo lead credits (1 per contact). Searches are free. Team balance after the run is reported in 13-icp-prospect-list.md.
A7: Email quality | B7: 193 verified work emails, 5 extrapolated, 21 unavailable (Apollo email_status field, column I of Contacts).
A8: Tabs | B8: Exec Summary (numbers) / Contacts (all 219, one row each) / Companies (122) / Approach Playbook (per segment: buying center, message, channels, rooms, proof, timing).
A9: Legend | B9: No cells require filling in; this is a data deliverable. Yellow cells on Exec Summary are hardcoded Apollo-reported totals (source noted beside them); all other summary numbers are formulas over the Contacts/Companies tabs.
A10: Compliance note | B10: Contact data is Apollo-licensed B2B data pulled under the team's Apollo seat; use per your outbound/GDPR policy (legitimate-interest B2B outreach; include opt-outs in DACH sequences).

Sheet Exec Summary
A1: Lio ICP Prospect List - Executive Summary
A2: Sourced via Apollo 2026-08-31 - formulas count the Contacts tab; yellow cells are Apollo-reported database totals (source: pagination.total_entries per search)
A4: Segment | B4: Contacts on list | C4: Verified emails | D4: Any email | E4: Apollo total buyers | F4: Apollo total companies | G4: Companies on list
A5: DACH Industrial | B5: =COUNTIF(Contacts!$B:$B,A5) | C5: =COUNTIFS(Contacts!$B:$B,A5,Contacts!$I:$I,"verified") | D5: =COUNTIFS(Contacts!$B:$B,A5,Contacts!$H:$H,"<>") | E5: 851 | F5: 153 | G5: =COUNTIF(Companies!$B:$B,A5)
A6: Insurance & FS | B6: =COUNTIF(Contacts!$B:$B,A6) | C6: =COUNTIFS(Contacts!$B:$B,A6,Contacts!$I:$I,"verified") | D6: =COUNTIFS(Contacts!$B:$B,A6,Contacts!$H:$H,"<>") | E6: 156 | F6: 34 | G6: =COUNTIF(Companies!$B:$B,A6)
A7: US GBS & BPO Owners | B7: =COUNTIF(Contacts!$B:$B,A7) | C7: =COUNTIFS(Contacts!$B:$B,A7,Contacts!$I:$I,"verified") | D7: =COUNTIFS(Contacts!$B:$B,A7,Contacts!$H:$H,"<>") | E7: 895 | F7: 1665 | G7: =COUNTIF(Companies!$B:$B,A7)
A8: Utilities & Mobility | B8: =COUNTIF(Contacts!$B:$B,A8) | C8: =COUNTIFS(Contacts!$B:$B,A8,Contacts!$I:$I,"verified") | D8: =COUNTIFS(Contacts!$B:$B,A8,Contacts!$H:$H,"<>") | E8: 343 | F8: 81 | G8: =COUNTIF(Companies!$B:$B,A8)
A9: TOTAL | B9: =SUM(B5:B8) | C9: =SUM(C5:C8) | D9: =SUM(D5:D8) | E9: =SUM(E5:E8) | F9: =SUM(F5:F8) | G9: =SUM(G5:G8)
A11: Seniority mix (list) | D11: Email status (list)
A12: c_suite | B12: =COUNTIF(Contacts!$G:$G,A12) | D12: verified | E12: =COUNTIF(Contacts!$I:$I,D12)
A13: head | B13: =COUNTIF(Contacts!$G:$G,A13) | D13: extrapolated | E13: =COUNTIF(Contacts!$I:$I,D13)
A14: vp | B14: =COUNTIF(Contacts!$G:$G,A14) | D14: unavailable | E14: =COUNTIF(Contacts!$I:$I,D14)
A15: director | B15: =COUNTIF(Contacts!$G:$G,A15)
A17: Search filters per segment: documented in 13-icp-prospect-list.md (locations, employee ranges, revenue floors, NAICS codes, title lists). Re-run the same filters in Apollo to refill the list; ~2,000 more titled buyers remain unpulled.

Sheet Contacts
A1: # | B1: Segment | C1: Name | D1: Title | E1: Company | F1: Company domain | G1: Seniority | H1: Email | I1: Email status | J1: LinkedIn URL | K1: Location | L1: Company employees | M1: Company industry | N1: Apollo person ID
A2: 1 | B2: DACH Industrial | C2: Frank Arendt | D2: Chief Procurement Officer | E2: Barry Callebaut Group | F2: barry-callebaut.com | G2: c_suite | H2: frank_arendt@barry-callebaut.com | I2: verified | J2: http://www.linkedin.com/in/frank-arendt-geneva | K2: Zuerich, Switzerland | L2: 14000 | M2: food production | N2: 66f41063d0097300015aa080
A3: 2 | B3: DACH Industrial | C3: Christine Berg | D3: Chief Procurement Officer | E3: Beiersdorf | F3: beiersdorf.com | G3: c_suite | H3: christine.berg@beiersdorf.com | I3: verified | J3: http://www.linkedin.com/in/christine-berg-41925b26 | K3: Hamburg, Germany | L3: 22000 | M3: cosmetics | N3: 610955967b1bdb00018b2331
A4: 3 | B4: DACH Industrial | C4: Harry Bloechlinger | D4: Chief Procurement Officer | E4: Bühler Group | F4: buhlergroup.com | G4: c_suite | H4: harry.bloechlinger@buhlergroup.com | I4: verified | J4: http://www.linkedin.com/in/harry-bloechlinger | K4: Uzwil, Switzerland | L4: 13000 | M4: machinery | N4: 6764f829d1ec910001a18540
A5: 4 | B5: DACH Industrial | C5: Nicola Comiotto | D5: Chief Procurement Officer | E5: Clariant | F5: clariant.com | G5: c_suite | H5: nicola.comiotto@clariant.com | I5: verified | J5: http://www.linkedin.com/in/nicola-comiotto-3b58a5135 | K5: Basel, Switzerland | L5: 11000 | M5: chemicals | N5: 622ef3d583d3560001cadd7b
A6: 5 | B6: DACH Industrial | C6: Rene Schwalm | D6: Chief Procurement Officer | E6: Dürr Group | F6: durr-group.com | G6: c_suite | H6: rene.schwalm@durr.com | I6: verified | J6: http://www.linkedin.com/in/ren%c3%a9-schwalm-15b5bb136 | K6: Bietigheim-Bissingen, Germany | L6: 18000 | M6: machinery | N6: 5d45e329a3ae613e1bd50f00
A7: 6 | B7: DACH Industrial | C7: Patrick Frings | D7: Chief Procurement Officer / VP Global Procurement | E7: ENERCON | F7: enercon.com | G7: c_suite | H7: patrick.frings@enercon.de | I7: verified | J7: http://www.linkedin.com/in/patrick-frings76 | K7: Muenster, Germany | L7: 13000 | M7: civil engineering | N7: 60b5fb90796d56000177eeaa
A8: 7 | B8: DACH Industrial | C8: Zoe Ren | D8: Chief Procurement Officer | E8: Ferring Pharmaceuticals | F8: ferring.com | G8: c_suite | H8: zoe.ren@ferring.com | I8: verified | J8: http://www.linkedin.com/in/zoe-ren-4b26ba7 | K8: Lausanne, Switzerland | L8: 7000 | M8: pharmaceuticals | N8: 66f7b7885812e80001a4cdda
A9: 8 | B9: DACH Industrial | C9: Thomas-Garry Stiller | D9: Senior Vice President & Chief Procurement Officer | E9: HARTMANN GROUP | F9: hartmann.info | G9: c_suite | H9: thomas-garry.stiller@hartmann.info | I9: verified | J9: http://www.linkedin.com/in/thomas-garry-stiller-090b697 | K9: Ulm, Germany | L9: 11000 | M9: medical devices | N9: 60ffdb790ec80d0001419c7e
A10: 9 | B10: DACH Industrial | C10: Jochen Pfister | D10: Chief Procurement Officer | E10: HENSOLDT | F10: hensoldt.net | G10: c_suite | H10: jochen.pfister@hensoldt.net | I10: verified | J10: http://www.linkedin.com/in/jochen-pfister-38a65337 | K10: Germany | L10: 9400 | M10: defense & space | N10: 54a7e7a6746869730ab04457
A11: 10 | B11: DACH Industrial | C11: Mathan Durairaj | D11: Chief Procurement Officer | E11: Holcim | F11: holcim.com | G11: c_suite | H11: mathan.durairaj@lafargeholcim.com | I11: verified | J11: http://www.linkedin.com/in/mathan-durairaj-59156791 | K11: Thalwil, Switzerland | L11: 19000 | M11: construction | N11: 678c2af3f847860001bea839
A12: 11 | B12: DACH Industrial | C12: Stefan Thomas | D12: Chief Procurement Officer | E12: INNIO Group | F12: innio.com | G12: c_suite | H12: stefan.thomas@innio.com | I12: verified | J12: http://www.linkedin.com/in/stefan-thomas-198054a0 | K12: Austria | L12: 5300 | M12: machinery | N12: 60e80c79aa6963000147f7fa
A13: 12 | B13: DACH Industrial | C13: Samuel Cochon | D13: Chief Procurement Officer | E13: MANN+HUMMEL | F13: mann-hummel.com | G13: c_suite | H13: samuel.cochon@mann-hummel.com | I13: verified | J13: http://www.linkedin.com/in/samuel-cochon-a5623b16 | K13: Lausanne, Switzerland | L13: 22000 | M13: environmental services | N13: 6634791866173900075a4d32
A14: 13 | B14: DACH Industrial | C14: Johan Keerberg | D14: Chief Procurement Officer | E14: Migros Industrie | F14: migrosindustrie.ch | G14: c_suite | H14: johan.keerberg@migrosindustrie.ch | I14: verified | J14: http://www.linkedin.com/in/johan-keerberg-78737120 | K14: Zuerich, Switzerland | L14: 13000 | M14: food production | N14: 60a28926f7300b0001d31cac
A15: 14 | B15: DACH Industrial | C15: Lynn Proft | D15: Chief Procurement Officer | E15: Sandoz | F15: sandoz.com | G15: c_suite | I15: unavailable | J15: http://www.linkedin.com/in/lynn-de-proft | K15: Switzerland | L15: 23000 | M15: pharmaceuticals | N15: 687e94e38867970001fa8dd4
A16: 15 | B16: DACH Industrial | C16: Matteo Stefani | D16: Chief Procurement Officer - Head of Global Procurement | E16: Straumann Group | F16: straumann.com | G16: c_suite | I16: unavailable | J16: http://www.linkedin.com/in/matteostefani76 | K16: Switzerland | L16: 11000 | M16: medical devices | N16: 60ed6dd88166e90001e366d5
A17: 16 | B17: DACH Industrial | C17: Viktor Oberst | D17: Head of Purchasing | E17: ACO Group | F17: aco.com | G17: head | H17: viktor.oberst@aco.com | I17: verified | J17: http://www.linkedin.com/in/viktor-oberst-8506692b6 | K17: Bad Oldesloe, Germany | L17: 5500 | M17: architecture & planning | N17: 66bb0790d9dcad000106897e
A18: 17 | B18: DACH Industrial | C18: Stefan Schmidt | D18: Head of Purchasing | E18: BENTELER Group | F18: benteler.com | G18: head | H18: stefan.schmidt@benteler.com | I18: verified | J18: http://www.linkedin.com/in/stefan-schmidt-650ba1b8 | K18: Bielefeld, Germany | L18: 23000 | M18: automotive | N18: 60deab77cd462600012d0f62
A19: 18 | B19: DACH Industrial | C19: Vanessa Niederer | D19: Head of Purchasing | E19: Constantia Flexibles | F19: cflex.com | G19: head | H19: vanessa.niederer@cflex.com | I19: verified | J19: http://www.linkedin.com/in/vanessa-niederer-kudlacek-356a02153 | K19: Vienna, Austria | L19: 9600 | M19: packaging & containers | N19: 61388ef161b1e2000150bd95
A20: 19 | B20: DACH Industrial | C20: Daniel Azopardo | D20: Head of Procurement Indirect Materials & Services | E20: DAW SE | F20: daw.de | G20: head | I20: unavailable | J20: http://www.linkedin.com/in/daniel-miret-azopardo-88a6ab29 | K20: Seeheim-Jugenheim, Germany | L20: 6000 | M20: building materials | N20: 615077f6cf1a8e00018e77e7
A21: 20 | B21: DACH Industrial | C21: Ole Struve | D21: Head of Purchasing | E21: Dräger | F21: draeger.com | G21: head | H21: ole.struve@draeger.com | I21: verified | J21: http://www.linkedin.com/in/ole-struve-046b3234a | K21: Germany | L21: 17000 | M21: medical devices | N21: 6821a2add80d8b0001ba33dd
A22: 21 | B22: DACH Industrial | C22: Florian Noesterer | D22: Head of Purchasing | E22: ENGEL | F22: engelglobal.com | G22: head | H22: florian.noesterer@engel.at | I22: verified | J22: http://www.linkedin.com/in/florian-noesterer-a07381105 | K22: Austria | L22: 7000 | M22: machinery | N22: 60b3338990c70a000145f86f
A23: 22 | B23: DACH Industrial | C23: Jens Carrle | D23: Leiter Einkauf und Logistik | E23: ElringKlinger | F23: elringklinger.de | G23: head | H23: jens.carrle@elringklinger.com | I23: verified | J23: http://www.linkedin.com/in/jens-carrle-564276160 | K23: Germany | L23: 9100 | M23: automotive | N23: 60ba43e8dab34b00013985c4
A24: 23 | B24: DACH Industrial | C24: Sascha Horvath | D24: Head of Purchasing | E24: FORVIA HELLA | F24: hella.com | G24: head | H24: sascha.horvath@hella.com | I24: verified | J24: http://www.linkedin.com/in/sascha-horvath-597501181 | K24: Grosspetersdorf, Austria | L24: 37000 | M24: automotive | N24: 6024e156009d7c0001510b01
A25: 24 | B25: DACH Industrial | C25: Birger Diesem | D25: Head of Purchasing | E25: GMH Gruppe | F25: gmh-gruppe.de | G25: head | H25: birger.diesem@gmh-gruppe.de | I25: verified | J25: http://www.linkedin.com/in/birger-diesem-1a73b971 | K25: Bonn, Germany | L25: 6000 | M25: mining & metals | N25: 57dfa435a6da980b38c4b9de
A26: 25 | B26: DACH Industrial | C26: Andre Suter | D26: Head of Indirect Procurement | E26: Geberit | F26: geberit.com | G26: head | H26: andre.suter@geberit.com | I26: verified | J26: http://www.linkedin.com/in/andr%c3%a9-a-suter-a1a03647 | K26: Zuerich, Switzerland | L26: 12000 | M26: building materials | N26: 54a76e957468696de75d0a34
A27: 26 | B27: DACH Industrial | C27: Ilona Piekoszewska | D27: Global Head Indirect Procurement (Materials and Services) | E27: Givaudan | F27: givaudan.com | G27: head | H27: ilona.piekoszewska@givaudan.com | I27: verified | J27: http://www.linkedin.com/in/ilona-piekoszewska-mba-85057152 | K27: Pregny-Chambesy, Switzerland | L27: 18000 | M27: chemicals | N27: 60745c9ff8d4090001f62786
A28: 27 | B28: DACH Industrial | C28: Kati Bensch | D28: Head of Procurement Excellence | E28: HARTMANN GROUP | F28: hartmann.info | G28: head | H28: kati.bensch@hartmann.info | I28: verified | J28: http://www.linkedin.com/in/kati-bensch-18ab1b10 | K28: Ulm, Germany | L28: 11000 | M28: medical devices | N28: 66f9d7a583ba0c00016d6249
A29: 28 | B29: DACH Industrial | C29: Christian Lima-Wirth | D29: Head of Purchasing | E29: HOERBIGER | F29: hoerbiger.com | G29: head | H29: christian.lima-wirth@hoerbiger.com | I29: verified | J29: http://www.linkedin.com/in/christian-lima-wirth-00330b101 | K29: Vienna, Austria | L29: 6500 | M29: machinery | N29: 67cef6d7ea3a6b0001a2105d
A30: 29 | B30: DACH Industrial | C30: Markus Klein | D30: Leiter Einkauf Nichtproduktionsmaterial | E30: HYDAC Group | F30: hydac.com | G30: head | H30: markus.klein@hydac.com | I30: verified | J30: http://www.linkedin.com/in/markus-klein-612245a1 | K30: Germany | L30: 11000 | M30: machinery | N30: 57dd5f2ca6da987b3d3dc0a5
A31: 30 | B31: DACH Industrial | C31: Reinhard Pohl | D31: Leiter Einkauf Prozesse & Controlling | E31: Heraeus | F31: heraeus.com | G31: head | I31: unavailable | J31: http://www.linkedin.com/in/reinhard-pohl-08718497 | K31: Germany | L31: 16000 | M31: chemicals | N31: 54a732897468696b7fe61f1e
A32: 31 | B32: DACH Industrial | C32: Tobias Muehlens | D32: Head of Digital Procurement Tools & Processes @ Procurement Center of Competence | E32: Heraeus | F32: heraeus.com | G32: head | H32: tobias.muehlens@heraeus.com | I32: verified | J32: http://www.linkedin.com/in/tobiasmuehlens | K32: Hanau, Germany | L32: 16000 | M32: chemicals | N32: 6065715b1a18db0001965c63
A33: 32 | B33: DACH Industrial | C33: Gottfried Deuble | D33: Leiter Einkauf Deutschland | E33: Häfele SE & Co KG | F33: haefele.de | G33: head | H33: gottfried.deuble@haefele.de | I33: verified | J33: http://www.linkedin.com/in/gottfried-deuble-0222157 | K33: Wildberg, Germany | L33: 8000 | M33: furniture | N33: 54aa4331746869261b471200
A34: 33 | B34: DACH Industrial | C34: Florian Kraemer | D34: Head of Indirect Procurement & AI Procurement Lead | E34: Intersnack Group | F34: intersnackgroup.com | G34: head | H34: f.kraemer@intersnackgroup.com | I34: verified | J34: http://www.linkedin.com/in/florian-kr%c3%a4mer | K34: Duesseldorf, Germany | L34: 14000 | M34: food production | N34: 670653496ff1ff0001c8fe46
A35: 34 | B35: DACH Industrial | C35: Mara Hillermeier | D35: Head of Procurement Excellence Europe | E35: KOSTAL Group | F35: kostal.com | G35: head | H35: m.hillermeier@kostal.com | I35: verified | J35: http://www.linkedin.com/in/mara-hillermeier-6ab189112 | K35: Germany | L35: 21000 | M35: automotive | N35: 57d48018a6da9853c6d2c209
A36: 35 | B36: DACH Industrial | C36: Stefanie Schlitt | D36: Head of Indirect Procurement | E36: KSB Company | F36: ksb.com | G36: head | H36: stefanie.schlitt@ksb.com | I36: verified | J36: http://www.linkedin.com/in/stefanie-schlitt-52a4691b5 | K36: Kitzingen, Germany | L36: 9300 | M36: machinery | N36: 614d9220028cae0001c06ad3
A37: 36 | B37: DACH Industrial | C37: Karoline Strobl | D37: Head of Group Indirect Procurement | E37: KUKA | F37: kuka.com | G37: head | H37: karoline.strobl@kuka.com | I37: verified | J37: http://www.linkedin.com/in/karoline-strobl-94995538 | K37: Munich, Germany | L37: 16000 | M37: machinery | N37: 557132917369641423d10400
A38: 37 | B38: DACH Industrial | C38: Michael Proch | D38: Head of Indirect Category Management & Procurement Excellence (Global & EMEA) | E38: Knauf | F38: knauf.com | G38: head | H38: michael.proch@knauf.com | I38: verified | J38: http://www.linkedin.com/in/proch | K38: Wuerzburg, Germany | L38: 44000 | M38: building materials | N38: 66f8a5461fb6a7000101b5b8
A39: 38 | B39: DACH Industrial | C39: Udo Mayer | D39: Leiter Einkauf & Logistik | E39: Lenzing Group | F39: lenzing.com | G39: head | I39: unavailable | J39: http://www.linkedin.com/in/udo-mayer-1b903714 | K39: Frankfurt, Germany | L39: 8300 | M39: chemicals | N39: 54a753b1746869622040522a
A40: 39 | B40: DACH Industrial | C40: Herfried Holzer | D40: Strategic Procurement, Head of Indirect Purchasing | E40: Lohmann & Rauscher | F40: lohmann-rauscher.com | G40: head | H40: herfried.holzer@at.lrmed.com | I40: verified | J40: http://www.linkedin.com/in/herfried-holzer-b2993130a | K40: Vienna, Austria | L40: 5400 | M40: medical devices | N40: 6689cbd73dbef000018ec9cc
A41: 40 | B41: DACH Industrial | C41: Cesare Gallo | D41: Head of Indirect Procurement, Switzerland and Europe | E41: Lonza | F41: lonza.com | G41: head | H41: cesare.gallo@lonza.com | I41: verified | J41: http://www.linkedin.com/in/cesare-gallo | K41: Zuerich, Switzerland | L41: 19000 | M41: pharmaceuticals | N41: 698858885e36020001bc2fd7
A42: 41 | B42: DACH Industrial | C42: Paul Pox | D42: Leiter Einkauf NPM Deutschland | E42: MAHLE | F42: mahle.com | G42: head | H42: paul.pox@mahle.com | I42: verified | J42: http://www.linkedin.com/in/paul-pox-18911415b | K42: Stuttgart, Germany | L42: 8100 | M42: automotive | N42: 5ddc3103c19eee00010d8750
A43: 42 | B43: DACH Industrial | C43: Ruth Leffers | D43: Head of Procurement Group Machinery & Indirect Material | E43: MEYER WERFT | F43: meyerwerft.de | G43: head | H43: ruth.leffers@meyerwerft.de | I43: verified | J43: http://www.linkedin.com/in/ruth-leffers-469289210 | K43: Papenburg, Germany | L43: 5200 | M43: shipbuilding | N43: 61ea671c6b02a500019dfcfe
A44: 43 | B44: DACH Industrial | C44: Amir Behrouz | D44: Head of Purchasing | E44: Mubea | F44: mubea.com | G44: head | H44: amir.behrouz@mubea.com | I44: verified | J44: http://www.linkedin.com/in/amir-behrouz | K44: Kreuzlingen, Switzerland | L44: 18000 | M44: automotive | N44: 5dde20c0d597f80001c02eff
A45: 44 | B45: DACH Industrial | C45: Silvio Hohm | D45: Head of Indirect Procurement | E45: PALFINGER AG | F45: palfinger.com | G45: head | H45: h.silvio@palfinger.com | I45: extrapolated | J45: http://www.linkedin.com/in/silvio-hohm-3b211787 | K45: Salzburg, Austria | L45: 13000 | M45: machinery | N45: 5ffb25df72b9cb000185b170
A46: 45 | B46: DACH Industrial | C46: Rene Hirzberger | D46: Head of Indirect Procurement & Logistics Europe, CIS & Türkiye | E46: RHI Magnesita | F46: rhimagnesita.com | G46: head | H46: rene.hirzberger@rhimagnesita.com | I46: verified | J46: http://www.linkedin.com/in/rene-hirzberger-a49a85166 | K46: Austria | L46: 16000 | M46: automotive | N46: 611a95299957df000143bd2b
A47: 46 | B47: DACH Industrial | C47: Jean-Baptiste Peau-Ruiz | D47: Head of Procurement - Professional Services and Digital Technologies | E47: ROLEX | F47: rolex.com | G47: head | H47: jean-baptiste.peau-ruiz@rolex.com | I47: verified | J47: http://www.linkedin.com/in/jean-baptiste-peau-ruiz-75b343b6 | K47: Geneva, Switzerland | L47: 20000 | M47: luxury goods & jewelry | N47: 60ddd86c5dd5a20001b1ae8b
A48: 47 | B48: DACH Industrial | C48: Enrico Scheutzel | D48: Leiter Indirekter Einkauf und Fuhrpark | E48: Radeberger Gruppe KG | F48: radeberger-gruppe.de | G48: head | H48: e.scheutzel@radeberger-gruppe.de | I48: verified | J48: http://www.linkedin.com/in/enricoscheutzel73 | K48: Balve, Germany | L48: 8000 | M48: food production | N48: 6041d9f7ebf86900014a9831
A49: 48 | B49: DACH Industrial | C49: Johannes Dittrich | D49: Head of Procurement and Purchasing | E49: Rohde & Schwarz | F49: rohde-schwarz.com | G49: head | H49: johannes.dittrich@rohde-schwarz.com | I49: verified | J49: http://www.linkedin.com/in/johannes-dittrich-b3831753 | K49: Munich, Germany | L49: 15000 | M49: telecommunications | N49: 54a51e38746869367617417e
A50: 49 | B50: DACH Industrial | C50: Francesco Medde | D50: Leiter Einkauf u. Produktmanagementt | E50: SFS Group | F50: sfs.com | G50: head | H50: francesco.medde@sfs.com | I50: extrapolated | J50: http://www.linkedin.com/in/francesco-medde-7a115476 | K50: Switzerland | L50: 14000 | M50: mining & metals | N50: 54ec4b1d746869444cdbe378
A51: 50 | B51: DACH Industrial | C51: Michael Schuetze | D51: Head of Procurement for Indirect Spend & Services | E51: SMS group | F51: sms-group.com | G51: head | H51: michael.schuetze@sms-group.com | I51: verified | J51: http://www.linkedin.com/in/michael-schuetze-71439764 | K51: Moenchengladbach, Germany | L51: 14000 | M51: machinery | N51: 5ffb399916c14d0001fa8583
A52: 51 | B52: DACH Industrial | C52: Christian Fuchs | D52: Global Head of Indirect Procurement | E52: SWAROVSKI | F52: swarovski.com | G52: head | I52: unavailable | J52: http://www.linkedin.com/in/christian-fuchs-33b3454 | K52: Zuerich, Switzerland | L52: 18000 | M52: luxury goods & jewelry | N52: 6101007dd673650001657f58
A53: 52 | B53: DACH Industrial | C53: Marvin Bialek | D53: Leiter Einkauf Einkaufsexzellenz | E53: Salzgitter Flachstahl GmbH | F53: salzgitter-flachstahl.de | G53: head | H53: bialek.m@salzgitter-ag.de | I53: verified | J53: http://www.linkedin.com/in/marvin-bialek-ab4b80268 | K53: Peine, Germany | L53: 6000 | M53: mining & metals | N53: 641181f8535aa70001194e53
A54: 53 | B54: DACH Industrial | C54: Oweys Shahriari | D54: Head of Indirect Procurement & Car Body Procurement | E54: Stadler | F54: stadlerrail.com | G54: head | H54: oweys.shahriari@stadlerrail.com | I54: verified | J54: http://www.linkedin.com/in/oweys-philipp-shahriari | K54: Switzerland | L54: 19000 | M54: railroad manufacture | N54: 62126ac3da24e50001c25fb0
A55: 54 | B55: DACH Industrial | C55: Theophanis Haralampidis | D55: Head of Purchasing | E55: Syntegon | F55: syntegon.com | G55: head | H55: theophanis.haralampidis@syntegon.com | I55: verified | J55: http://www.linkedin.com/in/theophanis-haralampidis-15ab3815a | K55: Schopfheim, Germany | L55: 5900 | M55: machinery | N55: 5e88981c1bba1400013c27c5
A56: 55 | B56: DACH Industrial | C56: Marko Pastrik | D56: Head of Procurement Excellence | E56: Wacker Neuson Group | F56: wackerneusongroup.com | G56: head | H56: marko.pastrik@wackerneuson.com | I56: verified | J56: http://www.linkedin.com/in/marko-pastrik-8b02042b | K56: Munich, Germany | L56: 5900 | M56: machinery | N56: 66f277df894d960001d824ad
A57: 56 | B57: DACH Industrial | C57: Andreas Kessler | D57: Head of Indirect Procurement | E57: Wacker Neuson Group | F57: wackerneusongroup.com | G57: head | H57: andreas.kessler@wackerneuson.com | I57: verified | J57: http://www.linkedin.com/in/kessler-indirect | K57: Munich, Germany | L57: 5900 | M57: machinery | N57: 607d69b137643800019d093f
A58: 57 | B58: DACH Industrial | C58: Frank Schaefer | D58: Global Head of Corporate Procurement (Indirect, Excellence & Real Estate) | E58: ams OSRAM | F58: ams-osram.com | G58: head | H58: frank.schaefer@ams-osram.com | I58: verified | J58: http://www.linkedin.com/in/frank-sch%c3%a4fer-236964a6 | K58: Munich, Germany | L58: 20000 | M58: semiconductors | N58: 57de5ef3a6da987b4d982502
A59: 58 | B59: DACH Industrial | C59: Christophe Pianta | D59: Leiter Einkauf und Logistk | E59: dormakaba | F59: dormakabagroup.com | G59: head | I59: unavailable | J59: http://www.linkedin.com/in/christophe-pianta-8b8776b5 | K59: Aadorf, Switzerland | L59: 16000 | M59: building materials | N59: 55708a607369642c52670500
A60: 59 | B60: DACH Industrial | C60: Dirk Reinhardt | D60: Head of Procurement Indirect Material and Services | E60: thyssenkrupp Steel | F60: thyssenkrupp-steel.com | G60: head | H60: dirk-michael.reinhardt@thyssenkrupp-steel.com | I60: verified | J60: http://www.linkedin.com/in/dirk-michael-reinhardt-b680b2119 | K60: Duesseldorf, Germany | L60: 27000 | M60: mining & metals | N60: 57d73275a6da98648820f835
A61: 60 | B61: DACH Industrial | C61: Mauro Palomba | D61: Senior Director- Global Head of Indirect Procurement | E61: Sonova Group | F61: sonova.com | G61: director | H61: mauro.palomba@sonova.com | I61: verified | J61: http://www.linkedin.com/in/mauro-palomba-5476a14 | K61: Zuerich, Switzerland | L61: 18000 | M61: medical devices | N61: 54a728677468696b7f6f841a
A62: 61 | B62: Insurance & FS | C62: Selvi Ayranci | D62: Group Chief Procurement Officer Allianz SE and Allianz Technology | E62: Allianz | F62: allianz.com | G62: c_suite | H62: selvi.ayranci@allianz.com | I62: extrapolated | J62: http://www.linkedin.com/in/selviayranci | K62: Munich, Germany | L62: 157000 | M62: financial services | N62: 62034c6734a16200012d942a
A63: 62 | B63: Insurance & FS | C63: Sebastian Fass | D63: Chief Procurement Officer | E63: Helaba | F63: helaba.com | G63: c_suite | H63: sebastian.fass@helaba.de | I63: verified | J63: http://www.linkedin.com/in/drsebastianfass | K63: Frankfurt, Germany | L63: 6600 | M63: banking | N63: 60f7a98d392c4b00019d88e6
A64: 63 | B64: Insurance & FS | C64: Nick Dobney | D64: Chief Procurement Officer | E64: Pictet Group | F64: pictet.com | G64: c_suite | H64: ndobney@pictet.com | I64: verified | J64: http://www.linkedin.com/in/nick-dobney-91089b | K64: Geneva, Switzerland | L64: 5500 | M64: financial services | N64: 60f7a9c45cd05f0001a6c5c6
A65: 64 | B65: Insurance & FS | C65: Boris Brauner | D65: Chief Procurement Officer & Prokurist | E65: SIGNAL IDUNA Gruppe | F65: signal-iduna.de | G65: c_suite | H65: boris.brauner@signal-iduna.de | I65: verified | J65: http://www.linkedin.com/in/boris-brauner-1a679595 | K65: Hamburg, Germany | L65: 11000 | M65: insurance | N65: 54a483547468693676aa494d
A66: 65 | B66: Insurance & FS | C66: Georg Schoell | D66: Head of Procurement Transformation, Allianz SE | E66: Allianz | F66: allianz.com | G66: head | H66: georg.schoell@allianz.com | I66: verified | J66: http://www.linkedin.com/in/georg-sch%c3%b6ll-17672917b | K66: Regensburg, Germany | L66: 157000 | M66: financial services | N66: 66fe3f2cc16028000103ae83
A67: 66 | B67: Insurance & FS | C67: Kathrin Baumeister | D67: Head of Contract Management, Global Sourcing & Procurement | E67: Allianz | F67: allianz.com | G67: head | H67: kathrin.baumeister@allianz.com | I67: verified | J67: http://www.linkedin.com/in/kathrin-baumeister-930800a4 | K67: Munich, Germany | L67: 157000 | M67: financial services | N67: 54a50cac74686938ac1aed78
A68: 67 | B68: Insurance & FS | C68: Matthew Lehar | D68: Head of Procurement Analytics | E68: Allianz | F68: allianz.com | G68: head | H68: matthew.lehar@allianz.com | I68: verified | J68: http://www.linkedin.com/in/matthew-lehar | K68: Germany | L68: 157000 | M68: financial services | N68: 5c4d4de7f65125edb57d0e15
A69: 68 | B69: Insurance & FS | C69: Dirk Tormaehlen | D69: Head of Professional Services at Global Sourcing & Procurement | E69: Allianz | F69: allianz.com | G69: head | H69: dirk.tormaehlen@allianz.com | I69: verified | J69: http://www.linkedin.com/in/dirk-tormaehlen-631b1261 | K69: Germany | L69: 157000 | M69: financial services | N69: 60ae323001a952000147c32a
A70: 69 | B70: Insurance & FS | C70: Ludmila Cecan | D70: Global Head of Regional Procurement Coordination - Global Sourcing and Procurement | E70: Allianz | F70: allianz.com | G70: head | H70: ludmila.cecan@allianz.com | I70: extrapolated | J70: http://www.linkedin.com/in/ludmila-c-b5355292 | K70: Munich, Germany | L70: 157000 | M70: financial services | N70: 62b35d446f585900019416ec
A71: 70 | B71: Insurance & FS | C71: Joerg Dahmen | D71: Leiter Zentrale Dienste, Geschäftsführer HKV GmbH (Head of Procurement & Corporate Real Estate) | E71: BarmeniaGothaer | F71: barmeniagothaer.de | G71: head | H71: joerg.dahmen@gothaer.de | I71: verified | J71: http://www.linkedin.com/in/dr-j%c3%b6rg-dahmen-3b0b31219 | K71: Aachen, Germany | L71: 7600 | M71: insurance | N71: 61694c69d7a9db0001b44bee
... A74: 73 | B74: Insurance & FS | C74: Carsten Freilinger | D74: Head of Vendor Management Corporate Bank | E74: Deutsche Bank | F74: db.com | G74: head | H74: carsten.freilinger@db.com | I74: verified | J74: http://www.linkedin.com/in/carsten-freilinger-04752780 | K74: Frankfurt, Germany | L74: 90000 | M74: financial services | N74: 66f536dad92bc80001463be4
A75: 74 | B75: Insurance & FS | C75: Claus Worzfeld | D75: Head of Procurement Transformation | E75: Deutsche Bank | F75: db.com | G75: head | I75: unavailable | J75: http://www.linkedin.com/in/claus-worzfeld-57233b13 | K75: Hamburg, Germany | L75: 90000 | M75: financial services | N75: 60dc7855744abd00018b1c55
A76: 75 | B76: Insurance & FS | C76: Martin Konieczny | D76: Head of Procurement Services & Support | E76: Deutsche Bank | F76: db.com | G76: head | H76: martin.konieczny@db.com | I76: verified | J76: http://www.linkedin.com/in/martin-konieczny-1b5b732a7 | K76: Frankfurt, Germany | L76: 90000 | M76: financial services | N76: 66f867a200dcf80001f6286c
A77: 76 | B77: Insurance & FS | C77: Christian Schulze | D77: Head of Procurement Solutions & Support Europe | E77: Deutsche Bank | F77: db.com | G77: head | I77: unavailable | J77: http://www.linkedin.com/in/christian-schulze-1b114629 | K77: Celle, Germany | L77: 90000 | M77: financial services | N77: 693a80f22c722500011da8d6
A78: 77 | B78: Insurance & FS | C78: Stefan Schwind | D78: Head of Purchasing Department | E78: Deutsche Börse Group | F78: deutsche-boerse.com | G78: head | H78: stefan.schwind@deutsche-boerse.com | I78: verified | J78: http://www.linkedin.com/in/stefan-schwind-8877a01a1 | K78: Obernburg, Germany | L78: 15000 | M78: financial services | N78: 612a670f4ca5a5000186af95
A79: 78 | B79: Insurance & FS | C79: Thomas Hoevel | D79: Head of Strategic Procurement | E79: Generali Deutschland AG | F79: generali.de | G79: head | H79: thomas.hoevel@generali.de | I79: verified | J79: http://www.linkedin.com/in/thomas-h%c3%b6vel-573a80123 | K79: Cologne, Germany | L79: 9200 | M79: insurance | N79: 609bb8684105a5000185edf3
A80: 79 | B80: Insurance & FS | C80: Denis Bucher | D80: Head Group Procurement | E80: Helvetia Baloise Group | F80: helvetia-baloise.com | G80: head | H80: denis.bucher@baloise.com | I80: verified | J80: http://www.linkedin.com/in/denis-a-bucher-b348b445 | K80: Laufen, Switzerland | L80: 22000 | M80: insurance | N80: 6662a4bea2bebe000123be2f
A81: 80 | B81: Insurance & FS | C81: Laura Accetta | D81: Head of Procurement | E81: HypoVereinsbank - UniCredit - Deutschland | F81: hvb.de | G81: head | H81: laura.accetta@hvb.de | I81: extrapolated | J81: http://www.linkedin.com/in/laura-accetta-0093467 | K81: Germany | L81: 11000 | M81: banking | N81: 54a3b0e87468693442c1260b
A82: 81 | B82: Insurance & FS | C82: Timo Schuster | D82: Leiter Einkauf, Lizenzmanagement, IT- & Projekt-Controlling | E82: Konzern Versicherungskammer | F82: konzern-versicherungskammer.de | G82: head | H82: timo.schuster@vkb.de | I82: verified | J82: http://www.linkedin.com/in/timo-schuster | K82: Germany | L82: 7500 | M82: insurance | N82: 6664195af233b200012e523b
A83: 82 | B83: Insurance & FS | C83: Petra Posch-Zottl | D83: Head of Group / AT Category & Vendor Management | E83: Raiffeisen Bank International AG | F83: rbinternational.com | G83: head | H83: petra.posch-zottl@rbinternational.com | I83: verified | J83: http://www.linkedin.com/in/petra-posch-zottl-b4364a47 | K83: Austria | L83: 43000 | M83: banking | N83: 6041b64d878c030001959b8f
A84: 83 | B84: Insurance & FS | C84: Jochen Kamann | D84: Leiter Einkauf DWP | E84: Raiffeisen Group | F84: raiffeisen.ch | G84: head | H84: jochen.kamann@raiffeisen.ch | I84: verified | J84: http://www.linkedin.com/in/jochen-kamann-8149aa105 | K84: Kloten, Switzerland | L84: 13000 | M84: banking | N84: 57d8c114a6da98729bcd4be2
A85: 84 | B85: Insurance & FS | C85: Dirk Schneider | D85: Head of Purchasing | E85: Raiffeisen Group | F85: raiffeisen.ch | G85: head | I85: unavailable | J85: http://www.linkedin.com/in/dirk-schneider-9b6522128 | K85: Basel, Switzerland | L85: 13000 | M85: banking | N85: 67e1483f1a206400019d7d7a
A86: 85 | B86: Insurance & FS | C86: Roger Hellmueller | D86: Head of BCM & Sourcing | E86: Raiffeisen Group | F86: raiffeisen.ch | G86: head | H86: roger.hellmueller@raiffeisen.ch | I86: verified | J86: http://www.linkedin.com/in/hellmueller | K86: Zuerich, Switzerland | L86: 13000 | M86: banking | N86: 6095240e7020c0000133d0b4
A87: 86 | B87: Insurance & FS | C87: Pauline King | D87: Head Group Procurement | E87: Swiss Re | F87: swissre.com | G87: head | H87: pauline_king@swissre.com | I87: verified | J87: http://www.linkedin.com/in/pauline-h-king | K87: Basel, Switzerland | L87: 15000 | M87: insurance | N87: 683fddffc768cc0001b378b0
A88: 87 | B88: Insurance & FS | C88: Andreas Baldauf | D88: Head of Strategic Procurement | E88: UNIQA Insurance Group | F88: uniqagroup.com | G88: head | H88: andreas.baldauf@uniqa.at | I88: verified | J88: http://www.linkedin.com/in/andreas-b-a7a9aa3b | K88: Austria | L88: 15000 | M88: insurance | N88: 5d6177e380f93e3a5f13b9f3
A89: 88 | B89: Insurance & FS | C89: Stefan Schmitt | D89: Head of Central Procurement | E89: Volkswagen Financial Services | F89: vwfs.com | G89: head | H89: stefan.schmitt@vwfs.com | I89: verified | J89: http://www.linkedin.com/in/stefan-schmitt-265b88169 | K89: Germany | L89: 11000 | M89: financial services | N89: 66f955209901a20001a85c38
A90: 89 | B90: Insurance & FS | C90: Jaime Paiva | D90: Global Head of Procurement Excellence | E90: Zurich Insurance | F90: zurich.com | G90: head | I90: unavailable | J90: http://www.linkedin.com/in/jaimehpaiva | K90: Cologne, Germany | L90: 60000 | M90: insurance | N90: 6112a83476808d00016c44bb
A91: 90 | B91: Insurance & FS | C91: Jan Latussek | D91: Head Sourcing & Procurement Switzerland | E91: Zurich Insurance | F91: zurich.com | G91: head | H91: jan.latussek@zurich.com | I91: verified | J91: http://www.linkedin.com/in/jan-latussek-a7519b10 | K91: Zuerich, Switzerland | L91: 60000 | M91: insurance | N91: 60f2b303c5b6e40001eac132
A92: 91 | B92: Insurance & FS | C92: David Hagen | D92: Head of Procurement & Teamlead IT & EPS Procurement | E92: Zurich Insurance | F92: zurich.com | G92: head | H92: david.hagen@zurich.com | I92: verified | J92: http://www.linkedin.com/in/david-von-hagen-818b1a1a0 | K92: Bonn, Germany | L92: 60000 | M92: insurance | N92: 6139d9222dafda00019626c9
A93: 92 | B93: Insurance & FS | C93: Pierre Bruns | D93: Head of Claims Vendor & Input Management | E93: Zurich Insurance | F93: zurich.com | G93: head | H93: pierre.bruns@zurich.com | I93: verified | J93: http://www.linkedin.com/in/pierre-bruns-514775b3 | K93: Zuerich, Switzerland | L93: 60000 | M93: insurance | N93: 57df3f73a6da980af978df1d
A94: 93 | B94: Insurance & FS | C94: Andreas Hoenger | D94: Head of Purchasing | E94: Zürcher Kantonalbank | F94: zkb.ch | G94: head | I94: unavailable | J94: http://www.linkedin.com/in/andreas-h%c3%b6nger-67b63121a | K94: Zuerich, Switzerland | L94: 6700 | M94: banking | N94: 622ad0d744284a00013efc1b
A95: 94 | B95: Insurance & FS | C95: Juan Labrador | D95: Head of Purchasing | E95: Zürcher Kantonalbank | F95: zkb.ch | G95: head | I95: unavailable | J95: http://www.linkedin.com/in/juan-labrador-0077a37b | K95: Zuerich, Switzerland | L95: 6700 | M95: banking | N95: 57d786e8a6da9809deee6611
A96: 95 | B96: Insurance & FS | C96: Christian Mueller | D96: Leiter Einkauf IT und Marktdaten | E96: Zürcher Kantonalbank | F96: zkb.ch | G96: head | H96: christian.mueller@zkb.ch | I96: verified | J96: http://www.linkedin.com/in/christian-m%c3%bcller-5219a3134 | K96: Zuerich, Switzerland | L96: 6700 | M96: banking | N96: 5c65d02a80f93eb9449ad565
A97: 96 | B97: Insurance & FS | C97: Michael Brunner | D97: Leiter Einkauf Professional Services, Marketing & Real Estate | E97: Zürcher Kantonalbank | F97: zkb.ch | G97: head | H97: michael.brunner@zkb.ch | I97: verified | J97: http://www.linkedin.com/in/michael-brunner-030b4556 | K97: Bonstetten, Switzerland | L97: 6700 | M97: banking | N97: 60337a778994c30001b0088d
A98: 97 | B98: Insurance & FS | C98: Thomas Furrer | D98: Leiter Competence Center Einkauf | E98: Zürcher Kantonalbank | F98: zkb.ch | G98: head | H98: thomas.furrer@zkb.ch | I98: verified | J98: http://www.linkedin.com/in/thomas-furrer-61158b6 | K98: Risch-Rotkreuz, Switzerland | L98: 6700 | M98: banking | N98: 54a4d18a7468693676f5a165
A99: 98 | B99: Insurance & FS | C99: Nicolas Koenig | D99: VP-Head of Group Procurement | E99: ARAG | F99: arag.com | G99: vp | H99: nicolas.koenig@arag.de | I99: verified | J99: http://www.linkedin.com/in/nicolas-k%c3%b6nig-b00038211 | K99: Germany | L99: 6200 | M99: insurance | N99: 6129e82ef8401600017d5e4c
A100: 99 | B100: Insurance & FS | C100: Ekaterina Samokhvalova | D100: Head of Category (VP) DWS Group | Global Procurement | E100: Deutsche Bank | F100: db.com | G100: vp | I100: unavailable | J100: http://www.linkedin.com/in/ekaterinasamokhvalova | K100: Berlin, Germany | L100: 90000 | M100: financial services | N100: 655c5ca1e7e618000191a685
A101: 100 | B101: Insurance & FS | C101: Rolf Seifert | D101: Executive Director - Regional Head Procurement EMEA | E101: UBS | F101: ubs.com | G101: director | H101: rolf.seifert@ubs.com | I101: verified | J101: http://www.linkedin.com/in/rolfseifert | K101: Zuerich, Switzerland | L101: 107000 | M101: financial services | N101: 54a72f2a74686965d939091d
A102: 101 | B102: US GBS & BPO Owners | C102: Rebecca Marshall | D102: Chief Procurement Officer and SVP Global Business Services | E102: ServiceNow | F102: servicenow.com | G102: c_suite | H102: rebecca.marshall@servicenow.com | I102: verified | J102: http://www.linkedin.com/in/rebecca-marshall-46b3067 | K102: West Palm Beach, United States | L102: 30000 | M102: information technology & services | N102: 66f70d909738050001997946
...

Sheet Companies
A1: # | B1: Segment | C1: Company | D1: Domain | E1: HQ | F1: Employees | G1: Revenue | H1: Industry | I1: Why it fits Lio's ICP
A2: 1 | B2: DACH Industrial | C2: TRUMPF | D2: trumpf.com | E2: Ditzingen, Germany | G2: 5.9B | H2: Machine tools / laser technology (NAICS 33324) | I2: Family-owned German Mittelstand machine-tool champion in the EUR 1-12B band
A3: 2 | B3: DACH Industrial | C3: Miele | D3: miele.com | E3: Guetersloh, Germany | G3: 6B | H3: Household appliances (NAICS 33522) | I3: Fourth-generation family-owned appliance manufacturer, conservative German enterprise IT
A4: 3 | B4: DACH Industrial | C4: Rohde & Schwarz | D4: rohde-schwarz.com | E4: Munich, Germany | G4: 3.7B | H4: Test & measurement / RF electronics (NAICS 33441) | I4: Family-owned Munich electronics group, same city and profile as Lio's reference base
A5: 4 | B5: DACH Industrial | C5: Dr. Oetker | D5: oetker.com | E5: Bielefeld, Germany | G5: 5B | H5: Food manufacturing (NAICS 311412) | I5: Classic family-owned German food group in the target revenue band
A6: 5 | B6: DACH Industrial | C6: Knorr-Bremse AG | D6: knorr-bremse.com | E6: Munich, Germany | G6: 9.2B | H6: Rail/commercial vehicle braking systems (NAICS 336510) | I6: Munich industrial with family-foundation anchor shareholder, EUR 9B revenue, SAP-heavy
A7: 6 | B7: DACH Industrial | C7: Giesecke+Devrient | D7: gi-de.com | E7: Munich, Germany | G7: 3.8B | H7: Security technology / banknote printing (NAICS 33911, 323111) | I7: Munich family-owned security-tech manufacturer, conservative enterprise estate
A8: 7 | B8: DACH Industrial | C8: Dräger | D8: draeger.com | E8: Luebeck, Germany | G8: 3.9B | H8: Medical & safety technology (NAICS 33911) | I8: Fifth-generation family-led medtech/safety manufacturer in band
A9: 8 | B9: DACH Industrial | C9: GEA Group | D9: gea.com | E9: Duesseldorf, Germany | G9: 6.4B | H9: Process engineering machinery (NAICS 333241) | I9: German process-machinery group, EUR 6.4B, classic SAP/Ariba estate
A10: 9 | B10: DACH Industrial | C10: KUKA | D10: kuka.com | E10: Augsburg, Germany | G10: 4.6B | H10: Robotics & automation (NAICS 333248) | I10: Bavarian robotics manufacturer in band; group indirect procurement lead surfaced in people search
A11: 10 | B11: DACH Industrial | C11: FORVIA HELLA | D11: hella.com | E11: Lippstadt, Germany | G11: 8.8B | H11: Automotive lighting & electronics (NAICS 33632) | I11: Founding-family-rooted German automotive supplier, EUR 8.8B
A12: 11 | B12: DACH Industrial | C12: MANN+HUMMEL | D12: mann-hummel.com | E12: Ludwigsburg, Germany | G12: 4.9B | H12: Filtration (NAICS 33911, 336390) | I12: Family-owned Swabian filtration leader; CPO and VP Procurement both surfaced
A13: 12 | B13: DACH Industrial | C13: Sartorius | D13: sartorius.com | E13: Goettingen, Germany | G13: 4.1B | H13: Lab & bioprocess equipment (NAICS 33324, 334516) | I13: German life-science equipment maker in band with complex direct/indirect spend
... A64: 63 | B64: US GBS & BPO Owners | C64: Microsoft | D64: microsoft.com | E64: Redmond, Washington, United States | G64: 331.8B | H64: Software / Cloud | I64: Mega-cap with huge indirect spend and mature GBS/outsourcing contracts to displace
A65: 64 | B65: US GBS & BPO Owners | C65: Google | D65: google.com | G65: 422.5B | H65: Internet / Technology | I65: Top-of-Fortune-500 scale indirect procurement and shared-services operations
A66: 65 | B66: US GBS & BPO Owners | C66: Apple | D66: apple.com | G66: 416.2B | H66: Consumer Electronics | I66: Largest-scale P2P volumes; enterprise procurement stack fits Lio's SAP/Ariba wedge
A67: 66 | B67: US GBS & BPO Owners | C67: Meta | D67: meta.com | G67: 201.0B | H67: Internet / Social Media | I67: Large US enterprise with centralized procurement ops and BPO-supported back office
A68: 67 | B68: US GBS & BPO Owners | C68: JPMorganChase | D68: jpmorganchase.com | G68: 279.7B | H68: Banking | I68: Massive shared-services and sourcing org; financial-services fit like Lio's Munich Re/ERGO base
A69: 68 | B69: US GBS & BPO Owners | C69: Citi | D69: citi.com | G69: 168.3B | H69: Banking | I69: Global GBS pioneer (two GBS/shared-services leaders surfaced in people search)
A70: 69 | B70: US GBS & BPO Owners | C70: Goldman Sachs | D70: goldmansachs.com | G70: 125.1B | H70: Investment Banking | I70: Large-enterprise financial services with heavy outsourced operations spend
A71: 70 | B71: US GBS & BPO Owners | C71: Mastercard | D71: mastercard.com | E71: Harrison, New York, United States | G71: 32.8B | H71: Payments | I71: F500 payments enterprise with global shared-services footprint
A72: 71 | B72: US GBS & BPO Owners | C72: Marsh | D72: marsh.com | E72: New York, New York, United States | G72: 27.0B | H72: Insurance Broking | I72: Insurance-sector fit (mirrors Lio's ERGO/Munich Re references) with large GBS org
A73: 72 | B73: US GBS & BPO Owners | C73: PepsiCo | D73: pepsico.com | G73: 93.9B | H73: Food & Beverage | I73: CPG giant with classic GBS/BPO-heavy procure-to-pay operations
A74: 73 | B74: US GBS & BPO Owners | C74: Procter & Gamble | D74: pg.com | G74: 87B | H74: Consumer Goods | I74: Invented the GBS model; prime target for agentic-BPO replacement pitch
A75: 74 | B75: US GBS & BPO Owners | C75: The Coca-Cola Company | D75: coca-cola.com | G75: 47.9B | H75: Beverages | I75: F500 CPG with outsourced finance/procurement shared services
A76: 75 | B76: US GBS & BPO Owners | C76: Mondelez International | D76: mondelezinternational.com | E76: Chicago, Illinois, United States | G76: 38.5B | H76: Food & Beverage | I76: Large GBS organization and heavy BPO contracts in P2P
A77: 76 | B77: US GBS & BPO Owners | C77: McCormick & Company | D77: mccormickcorporation.com | E77: Cockeysville, Maryland, United States | G77: 6.8B | H77: Food Manufacturing | I77: VP Head of GBS surfaced in people search; sized like Lio's Mittelstand-plus customers
A78: 77 | B78: US GBS & BPO Owners | C78: Cargill | D78: cargill.com | E78: Wayzata, Minnesota, United States | G78: 154B | H78: Agribusiness | I78: Largest US private company; sprawling shared-services and sourcing operations
A79: 78 | B79: US GBS & BPO Owners | C79: Bunge | D79: bunge.com | E79: Chesterfield, Missouri, United States | G79: 70.3B | H79: Agribusiness | I79: Global commodity trader with SAP-centric P2P at scale
A80: 79 | B80: US GBS & BPO Owners | C80: Pfizer | D80: pfizer.com | G80: 62.6B | H80: Pharmaceuticals | I80: VP GBS surfaced in people search; pharma sector mirrors Lio's Zeiss/Schaeffler industrial base
A81: 80 | B81: US GBS & BPO Owners | C81: Johnson & Johnson | D81: jnj.com | E81: New Brunswick, New Jersey, United States | G81: 94.2B | H81: Pharma / MedTech | I81: Major GBS operator (DePuy Synthes GBS head also surfaced) with large BPO contracts
A82: 81 | B82: US GBS & BPO Owners | C82: Tesla | D82: tesla.com | E82: Austin, Texas, United States | G82: 94.8B | H82: Automotive | I82: Automotive/manufacturing fit matching Lio's Brose/Schaeffler references
A83: 82 | B83: US GBS & BPO Owners | C83: Dell Technologies | D83: dell.com | G83: 113.5B | H83: IT Hardware | I83: VP Indirect Procurement surfaced in people search; enormous indirect-spend org
A84: 83 | B84: US GBS & BPO Owners | C84: Cisco | D84: cisco.com | E84: San Jose, California, United States | G84: 56.7B | H84: Networking / Technology | I84: Large enterprise with mature source-to-pay and GBS functions
A85: 84 | B85: US GBS & BPO Owners | C85: Oracle | D85: oracle.com | G85: 67.4B | H85: Enterprise Software | I85: F500-scale procurement ops; large shared-services organization
A86: 85 | B86: US GBS & BPO Owners | C86: Salesforce | D86: salesforce.com | G86: 41.5B | H86: Enterprise Software | I86: VP Procurement Operations surfaced in people search; large indirect-spend buyer
A87: 86 | B87: US GBS & BPO Owners | C87: Adobe | D87: adobe.com | G87: 23.8B | H87: Software | I87: Large US enterprise buyer with centralized procurement operations
A88: 87 | B88: US GBS & BPO Owners | C88: LinkedIn | D88: linkedin.com | E88: Sunnyvale, California, United States | G88: 17.8B | H88: Internet / Professional Network | I88: Enterprise-scale shared services within the Microsoft family
A89: 88 | B89: US GBS & BPO Owners | C89: Netflix | D89: netflix.com | G89: 45.2B | H89: Media / Streaming | I89: F500 media enterprise with growing procurement-operations maturity
A90: 89 | B90: US GBS & BPO Owners | C90: The Walt Disney Company | D90: thewaltdisneycompany.com | G90: 97.3B | H90: Media & Entertainment | I90: Massive shared-services and outsourced back-office spend
A91: 90 | B91: US GBS & BPO Owners | C91: Nike | D91: nike.com | G91: 46.4B | H91: Apparel / Consumer Goods | I91: Global consumer brand with large indirect procurement and GBS footprint
A92: 91 | B92: US GBS & BPO Owners | C92: Marriott International | D92: marriott.com | E92: Bethesda, Maryland, United States | G92: 26.2B | H92: Hospitality | I92: VP Procurement Operations surfaced in people search; huge decentralized P2P volumes
A93: 92 | B93: US GBS & BPO Owners | C93: Lam Research | D93: lamresearch.com | E93: Fremont, California, United States | G93: 23.2B | H93: Semiconductor Equipment | I93: Industrial-manufacturing fit matching Lio's Schaeffler/Zeiss ICP
A94: 93 | B94: Utilities & Mobility | C94: Deutsche Bahn | D94: deutschebahn.com | E94: Berlin, Germany | G94: 31.7B | H94: Rail transport | I94: State-owned rail giant of the exact DB-class named in the segment; massively process-heavy SAP procurement across infrastructure, rolling stock and services
A95: 94 | B95: Utilities & Mobility | C95: Lufthansa Group | D95: lufthansagroup.com | E95: Cologne, Germany | G95: 41.3B | H95: Airlines | I95: Flagship DACH airline group explicitly Lufthansa-class for this segment; huge multi-BU indirect and MRO spend on legacy SAP stack
A96: 95 | B96: Utilities & Mobility | C96: Stadtwerke München (SWM) | D96: swm.de | E96: Munich, Germany | G96: 7.4B | H96: Municipal utility | I96: The named SWM target itself: municipal multi-utility plus transit, regulated public tendering, and local to Lio in Munich (Apollo record surfaced under a site-level label, deduped to SWM)
A97: 96 | B97: Utilities & Mobility | C97: E.ON | D97: eon.com | E97: Essen, Germany | G97: 92.3B | H97: Energy utility | I97: 70k+ employee regulated energy utility with enormous grid/services P2P volume on SAP
A98: 97 | B98: Utilities & Mobility | C98: RWE | D98: rwe.com | E98: Essen, Germany | G98: 18.1B | H98: Power generation | I98: Large listed German power producer; capital-intensive, process-heavy procurement in a regulated sector
A99: 98 | B99: Utilities & Mobility | C99: EnBW Energie Baden-Württemberg | D99: enbw.com | E99: Karlsruhe, Germany | G99: 40.3B | H99: Energy utility | I99: State-majority-owned utility (Land BW ownership) with public-procurement obligations and 25k+ employees
A100: 99 | B100: Utilities & Mobility | C100: Uniper | D100: uniper.energy | E100: Duesseldorf, Germany | G100: 71.5B | H100: Energy utility | I100: German-state-owned since the 2022 bailout; regulated, high-volume energy procurement organization
A101: 100 | B101: Utilities & Mobility | C101: Netze BW | D101: netze-bw.de | E101: Stuttgart, Germany | H101: Grid operator | I101: Regulated distribution grid operator (EnBW group) — tender-driven, documentation-heavy purchasing
A102: 101 | B102: Utilities & Mobility | C102: DB Cargo | D102: dbcargo.com | E102: Mainz, Germany | G102: 5.8B | H102: Rail freight | I102: DB's rail-freight arm; state-owned, SAP-based, asset-heavy procurement (record surfaced under a site-level label, deduped)
A103: 102 | B103: Utilities & Mobility | C103: Hapag-Lloyd | D103: hapag-lloyd.com | E103: Hamburg, Germany | G103: 21.8B | H103: Container shipping | I103: Global container line headquartered in Hamburg; large fleet/port/indirect spend in a process-heavy maritime business
A104: 103 | B104: Utilities & Mobility | C104: Fraport | D104: fraport.com | E104: Frankfurt, Germany | G104: 5.2B | H104: Airport operator | I104: Public-shareholder airport operator with regulated tendering across construction, security and operations
A105: 104 | B105: Utilities & Mobility | C105: Berliner Verkehrsbetriebe (BVG) | D105: bvg.de | E105: Berlin, Germany | G105: 2B | H105: Public transit | I105: Municipal transit authority — Stadtwerke-class public procurement rules and heavy vehicle/infrastructure buying
A106: 105 | B106: Utilities & Mobility | C106: Flix (FlixBus/FlixTrain) | D106: flixbus.com | E106: Munich, Germany | G106: 2.7B | H106: Mobility platform | I106: Munich mobility group at 2B+ revenue scaling procurement across bus/rail operations (record surfaced under a site-level label, deduped)
A107: 106 | B107: Utilities & Mobility | C107: Condor Airlines | D107: condor.com | E107: Neu-Isenburg, Germany | H107: Airlines | I107: German leisure airline rebuilding its own group functions post-Thomas-Cook — greenfield-ish procurement org in the airline class
A108: 107 | B108: Utilities & Mobility | C108: ÖBB | D108: oebb.at | E108: Vienna, Austria | G108: 7.2B | H108: Rail transport | I108: Austrian state railway — DB-analog with public tendering law and infrastructure-scale P2P
A109: 108 | B109: Utilities & Mobility | C109: VERBUND | D109: verbund.com | E109: Vienna, Austria | G109: 9.4B | H109: Hydro power utility | I109: Austria's state-majority hydro utility; regulated, capital-intensive procurement
A110: 109 | B110: Utilities & Mobility | C110: EVN | D110: evn.at | E110: Maria Enzersdorf, Austria | G110: 4.0B | H110: Energy utility | I110: Lower-Austria state-majority multi-utility (energy, water, waste) with public-sector purchasing processes
A111: 110 | B111: Utilities & Mobility | C111: Wiener Stadtwerke | D111: wienerstadtwerke.at | E111: Vienna, Austria | G111: 6.1B | H111: Municipal utility holding | I111: Vienna's municipal utility/transit holding — the Austrian SWM equivalent
A112: 111 | B112: Utilities & Mobility | C112: Wien Energie | D112: wienenergie.at | E112: Vienna, Austria | G112: 3.5B | H112: Energy utility | I112: Austria's largest regional energy provider (Wiener Stadtwerke group), municipal ownership and regulated buying
A113: 112 | B113: Utilities & Mobility | C113: Austrian Airlines | D113: austrian.com | E113: Vienna, Austria | G113: 2.9B | H113: Airlines | I113: Lufthansa Group carrier in Austria — airline-class MRO and indirect spend on group SAP processes
A114: 113 | B114: Utilities & Mobility | C114: cargo-partner | D114: cargo-partner.com | E114: Vienna area, Austria | G114: 1.8B | H114: Logistics/forwarding | I114: Austrian logistics group (now Nippon Express) at 1.8B — process-heavy multi-country transport procurement
A115: 114 | B115: Utilities & Mobility | C115: SBB CFF FFS | D115: sbb.ch | E115: Bern, Switzerland | G115: 14.7B | H115: Rail transport | I115: Swiss federal railways — state-owned, tender-bound, infrastructure-scale procurement (DB-class for CH)
A116: 115 | B116: Utilities & Mobility | C116: SBB Cargo | D116: sbbcargo.com | E116: Olten, Switzerland | G116: 1.1B | H116: Rail freight | I116: SBB's freight arm with its own procurement leadership; same regulated rail profile
A117: 116 | B117: Utilities & Mobility | C117: Swiss Post | D117: swisspost.ch | E117: Bern, Switzerland | G117: 9.2B | H117: Postal & logistics | I117: State-owned postal/logistics/mobility group (incl. PostBus) subject to public procurement law
A118: 117 | B118: Utilities & Mobility | C118: Swiss International Air Lines | D118: swiss.com | E118: Kloten, Switzerland | G118: 7.6B | H118: Airlines | I118: Lufthansa Group's Swiss flag carrier — airline-class spend within a group SAP landscape
A119: 118 | B119: Utilities & Mobility | C119: Axpo Group | D119: axpo.com | E119: Baden, Switzerland | G119: 9.3B | H119: Energy utility | I119: Cantonal-owned Swiss energy group with an active group CPO office and regulated, capital-heavy buying
... A123: 122 | B123: Utilities & Mobility | C123: Swissport | D123: swissport.com | E123: Opfikon, Switzerland | G123: 4.6B | H123: Aviation ground services | I123: Global ground-handling leader from Zurich — high-volume, multi-station operational procurement in aviation

Sheet Approach Playbook
A1: Segment | B1: Buying center (who signs, who champions) | C1: Lead message | D1: Channel sequence | E1: Best rooms (from the event program) | F1: Proof points to lead with | G1: Timing triggers
A2: DACH Industrial (60 contacts / 851 in Apollo) | B2: CPO sponsors; COO/CFO is the economic buyer via the BPO/FTE line; Head of Procurement Excellence champions; CIO/CISO gatekeeps (ISO 27001 yes, SOC 2 not yet). | C2: Overlay, don't replace: agents operate your existing SAP/Ariba estate; 85% less manual work; ~120-FTE case at a Tier-1 manufacturer (EUR 7-9M/yr). | D2: Warm room first (BME/Handelsblatt/eLoesungstage), then German-language email + LinkedIn from a founder or AE, then Principals dinner invite. Cold email is the last resort in this culture, not the first. | E2: BME-Symposium Berlin (Nov 18-19) - SSOW DACH Berlin (Nov 17-19) - eLoesungstage (May 11-12, 2027) - Procurement Summit Hamburg (Jun 23-24, 2027) - Bots & Buyers EU (Oct 27-28) | F2: Schaeffler co-development MOU + COO quote; REHAU BME award + Porsche Consulting AI Impact Award 2026; 2-week integration. | G2: SAP/Ariba renewal windows; works-council-friendly re-roling narrative; family-owner conviction cycles (Maschinenbau-Gipfel attendance).
A3: Insurance & FS (40 contacts / 156 in Apollo) | B3: Head of Procurement / Sourcing & Vendor Management; compliance and audit functions in the room from day one. | C3: 100% indirect spend = the fastest agentic-BPO math in the portfolio; auditable 24/7 agents vs BPO black box, at ~7% of BPO cost. | D3: Reference-led: Munich Re "Agent Experience World" visit as the social proof; invite to a Lio office demo; then email the CPO office directly. | E3: DPW Amsterdam (Sep 30-Oct 1) - SSOW DACH Berlin (Nov 17-19) - Handelsblatt CPO Summit (Apr 6-7, 2027) | F3: Munich Re engagement (~30 procurement leaders through Lio's Munich showroom); ERGO instance live (ergo.asklio.ai); ISO 27001 + EU hosting. | G3: BPO/SSC contract renewals; DORA/outsourcing-audit pressure; year-end cost programs.
A4: US GBS & BPO Owners (60 contacts / 895 in Apollo) | B4: VP/Head of GBS, Shared Services, P2P/S2P GPOs - the people who SIGN outsourcing renewals. CPO is an ally, CFO decides. | C4: Your BPO costs 93% too much: same scope, ~7% of cost, 99.6% automation at 12 months, auditable, and you own the execution layer. | D4: Email-first (US norm) with the BPO-cost wedge, then SSOW/SIG room meetings booked around renewal windows; Petras (ex-Walmart) as sender/closer. | E4: SSON San Diego (Sep 14-17) - ProcureCon East Boston (Sep 28-30) - SIG Chicago (Oct 25-28) - SSOW Orlando (Mar 8-11, 2027) - Bots & Buyers NYC (Sep 23) | F4: Fortune-scale retail case (99.8% accuracy in 2 weeks, ~7% of BPO cost); Walmart engagement story via Petras; a16z backing. | G4: BPO contract renewal cycles (ask directly in sequence); GBS transformation mandates; "agentic AI" board directives.
A5: Utilities & Mobility (59 contacts / 343 in Apollo) | B5: Leiter Einkauf/Beschaffung + digitalization leads; works councils early; public-sector procurement rules at the Stadtwerke end. | C5: Regulated-grade autonomy: human-on-the-loop supervision, full audit trail, EU hosting - agents that pass an auditor's review. | D5: German-language webinar -> Bots & Buyers invite -> pilot proposal. Slow trust curve; do not lead with cold calls. | E5: BME circuit + SSOW DACH Berlin; Bots & Buyers EU (Deutsche Bahn, Lufthansa, SWM already in that room) | F5: Deutsche Bahn "Loom" pilot; DB/Lufthansa/SWM attendance at Bots & Buyers Clubhouse; TUEV SUED knowledge-base testimonial. | G5: Energy-cost pressure programs; digitalization budgets; Konzern efficiency programs.
